{
"meta":{"test_sets":[],"test_metrics":[],"learn_metrics":[{"best_value":"Min","name":"RMSE"}],"launch_mode":"Train","parameters":"","iteration_count":1000,"learn_sets":["learn"],"name":"experiment"},
"iterations":[
{"learn":[14.59871775],"iteration":0,"passed_time":0.1369564747,"remaining_time":136.8195182},
{"learn":[14.22518863],"iteration":1,"passed_time":0.1402593838,"remaining_time":69.98943253},
{"learn":[13.8866124],"iteration":2,"passed_time":0.1431667742,"remaining_time":47.57909131},
{"learn":[13.52356875],"iteration":3,"passed_time":0.1466751152,"remaining_time":36.52210367},
{"learn":[13.18870211],"iteration":4,"passed_time":0.1502570593,"remaining_time":29.9011548},
{"learn":[12.9124226],"iteration":5,"passed_time":0.1535128513,"remaining_time":25.43196236},
{"learn":[12.60003351],"iteration":6,"passed_time":0.1565740864,"remaining_time":22.21115254},
{"learn":[12.32990573],"iteration":7,"passed_time":0.1586398266,"remaining_time":19.6713385},
{"learn":[12.0660619],"iteration":8,"passed_time":0.1617326182,"remaining_time":17.80855829},
{"learn":[11.77309809],"iteration":9,"passed_time":0.1642815028,"remaining_time":16.26386878},
{"learn":[11.49227636],"iteration":10,"passed_time":0.1670007631,"remaining_time":15.01488679},
{"learn":[11.26264833],"iteration":11,"passed_time":0.1699852406,"remaining_time":13.99545148},
{"learn":[11.04260393],"iteration":12,"passed_time":0.1726626883,"remaining_time":13.10908257},
{"learn":[10.79916926],"iteration":13,"passed_time":0.1764003391,"remaining_time":12.42362388},
{"learn":[10.5541002],"iteration":14,"passed_time":0.1789575315,"remaining_time":11.75154457},
{"learn":[10.31918115],"iteration":15,"passed_time":0.1814567771,"remaining_time":11.15959179},
{"learn":[10.10004441],"iteration":16,"passed_time":0.183630481,"remaining_time":10.61816252},
{"learn":[9.894556723],"iteration":17,"passed_time":0.1859020287,"remaining_time":10.14198846},
{"learn":[9.690174082],"iteration":18,"passed_time":0.1880445598,"remaining_time":9.709037536},
{"learn":[9.506034866],"iteration":19,"passed_time":0.1900735219,"remaining_time":9.313602572},
{"learn":[9.338524633],"iteration":20,"passed_time":0.1922574542,"remaining_time":8.962859411},
{"learn":[9.170203312],"iteration":21,"passed_time":0.1940821001,"remaining_time":8.627831539},
{"learn":[9.010299969],"iteration":22,"passed_time":0.1961405136,"remaining_time":8.331707905},
{"learn":[8.843866678],"iteration":23,"passed_time":0.1980747054,"remaining_time":8.055038021},
{"learn":[8.690548059],"iteration":24,"passed_time":0.1998437737,"remaining_time":7.793907176},
{"learn":[8.555307687],"iteration":25,"passed_time":0.2013860921,"remaining_time":7.544232835},
{"learn":[8.413851302],"iteration":26,"passed_time":0.2030014048,"remaining_time":7.315569145},
{"learn":[8.29256019],"iteration":27,"passed_time":0.2045617643,"remaining_time":7.101215532},
{"learn":[8.162193833],"iteration":28,"passed_time":0.2060184944,"remaining_time":6.89806752},
{"learn":[8.040736294],"iteration":29,"passed_time":0.2073867664,"remaining_time":6.705505448},
{"learn":[7.921220278],"iteration":30,"passed_time":0.2088027755,"remaining_time":6.526770628},
{"learn":[7.809589039],"iteration":31,"passed_time":0.2100631044,"remaining_time":6.354408908},
{"learn":[7.699675801],"iteration":32,"passed_time":0.2114951679,"remaining_time":6.197449313},
{"learn":[7.60645267],"iteration":33,"passed_time":0.2129832207,"remaining_time":6.051229151},
{"learn":[7.498880302],"iteration":34,"passed_time":0.2141108639,"remaining_time":5.903342391},
{"learn":[7.401158744],"iteration":35,"passed_time":0.2156585088,"remaining_time":5.774855626},
{"learn":[7.306431077],"iteration":36,"passed_time":0.2171235087,"remaining_time":5.651079429},
{"learn":[7.223863468],"iteration":37,"passed_time":0.2184208749,"remaining_time":5.529496885},
{"learn":[7.143477682],"iteration":38,"passed_time":0.2197995926,"remaining_time":5.416087397},
{"learn":[7.062817131],"iteration":39,"passed_time":0.2210697977,"remaining_time":5.305675145},
{"learn":[6.990793435],"iteration":40,"passed_time":0.2223755413,"remaining_time":5.201418149},
{"learn":[6.931862224],"iteration":41,"passed_time":0.2233354528,"remaining_time":5.094175329},
{"learn":[6.858296558],"iteration":42,"passed_time":0.2245212333,"remaining_time":4.996902796},
{"learn":[6.786268161],"iteration":43,"passed_time":0.2259837877,"remaining_time":4.910011388},
{"learn":[6.717118549],"iteration":44,"passed_time":0.2271682627,"remaining_time":4.821015352},
{"learn":[6.652948106],"iteration":45,"passed_time":0.2285651737,"remaining_time":4.74024295},
{"learn":[6.589686076],"iteration":46,"passed_time":0.2299722133,"remaining_time":4.663053602},
{"learn":[6.531283097],"iteration":47,"passed_time":0.2312799336,"remaining_time":4.587052017},
{"learn":[6.471368031],"iteration":48,"passed_time":0.2324392891,"remaining_time":4.511219672},
{"learn":[6.416481395],"iteration":49,"passed_time":0.2333797491,"remaining_time":4.434215233},
{"learn":[6.369870822],"iteration":50,"passed_time":0.2346054864,"remaining_time":4.36550209},
{"learn":[6.325678067],"iteration":51,"passed_time":0.2356078379,"remaining_time":4.295312122},
{"learn":[6.275766122],"iteration":52,"passed_time":0.2366652716,"remaining_time":4.228717212},
{"learn":[6.224773967],"iteration":53,"passed_time":0.2375522053,"remaining_time":4.161562707},
{"learn":[6.182249254],"iteration":54,"passed_time":0.2385532503,"remaining_time":4.098778573},
{"learn":[6.139904173],"iteration":55,"passed_time":0.2395574469,"remaining_time":4.038254105},
{"learn":[6.100525536],"iteration":56,"passed_time":0.2404354388,"remaining_time":3.977730155},
{"learn":[6.062568564],"iteration":57,"passed_time":0.2413461169,"remaining_time":3.919793829},
{"learn":[6.030559288],"iteration":58,"passed_time":0.2422163855,"remaining_time":3.863146081},
{"learn":[5.997931376],"iteration":59,"passed_time":0.2430831052,"remaining_time":3.808301982},
{"learn":[5.964103835],"iteration":60,"passed_time":0.2440236739,"remaining_time":3.756364423},
{"learn":[5.933729724],"iteration":61,"passed_time":0.244909878,"remaining_time":3.705249445},
{"learn":[5.901932711],"iteration":62,"passed_time":0.2456851488,"remaining_time":3.654079117},
{"learn":[5.873727795],"iteration":63,"passed_time":0.2464807421,"remaining_time":3.604780854},
{"learn":[5.846485734],"iteration":64,"passed_time":0.2472907652,"remaining_time":3.557182546},
{"learn":[5.820630862],"iteration":65,"passed_time":0.2481587187,"remaining_time":3.511821868},
{"learn":[5.793646238],"iteration":66,"passed_time":0.2490811775,"remaining_time":3.468548337},
{"learn":[5.765388646],"iteration":67,"passed_time":0.2498715763,"remaining_time":3.424710428},
{"learn":[5.747073912],"iteration":68,"passed_time":0.2506521907,"remaining_time":3.381988254},
{"learn":[5.722315217],"iteration":69,"passed_time":0.2513850472,"remaining_time":3.339829913},
{"learn":[5.699970599],"iteration":70,"passed_time":0.2520650982,"remaining_time":3.298147553},
{"learn":[5.682732647],"iteration":71,"passed_time":0.2528512518,"remaining_time":3.258971689},
{"learn":[5.663525791],"iteration":72,"passed_time":0.2536147161,"remaining_time":3.220559477},
{"learn":[5.642381613],"iteration":73,"passed_time":0.2543724531,"remaining_time":3.18309313},
{"learn":[5.621404779],"iteration":74,"passed_time":0.2550398088,"remaining_time":3.145490975},
{"learn":[5.602460129],"iteration":75,"passed_time":0.2558996328,"remaining_time":3.111200799},
{"learn":[5.587337574],"iteration":76,"passed_time":0.256561917,"remaining_time":3.075411031},
{"learn":[5.572393026],"iteration":77,"passed_time":0.2572763638,"remaining_time":3.041138557},
{"learn":[5.558425806],"iteration":78,"passed_time":0.2579747456,"remaining_time":3.007528364},
{"learn":[5.541518902],"iteration":79,"passed_time":0.2587390702,"remaining_time":2.975499307},
{"learn":[5.526157283],"iteration":80,"passed_time":0.2595040135,"remaining_time":2.944249239},
{"learn":[5.511746977],"iteration":81,"passed_time":0.2603599529,"remaining_time":2.914761423},
{"learn":[5.504975022],"iteration":82,"passed_time":0.2608094327,"remaining_time":2.881472889},
{"learn":[5.493980522],"iteration":83,"passed_time":0.2616168404,"remaining_time":2.852869355},
{"learn":[5.480745463],"iteration":84,"passed_time":0.262446413,"remaining_time":2.825158446},
{"learn":[5.464052013],"iteration":85,"passed_time":0.2632839061,"remaining_time":2.798156862},
{"learn":[5.449143727],"iteration":86,"passed_time":0.2640778162,"remaining_time":2.771299381},
{"learn":[5.438255432],"iteration":87,"passed_time":0.264883088,"remaining_time":2.745152003},
{"learn":[5.425927931],"iteration":88,"passed_time":0.2656069801,"remaining_time":2.718741111},
{"learn":[5.412331217],"iteration":89,"passed_time":0.2663972816,"remaining_time":2.693572514},
{"learn":[5.400691499],"iteration":90,"passed_time":0.2671427028,"remaining_time":2.668491394},
{"learn":[5.391618744],"iteration":91,"passed_time":0.2681110277,"remaining_time":2.646139274},
{"learn":[5.380766572],"iteration":92,"passed_time":0.2689671958,"remaining_time":2.623153189},
{"learn":[5.372207183],"iteration":93,"passed_time":0.2697887712,"remaining_time":2.600304539},
{"learn":[5.362918837],"iteration":94,"passed_time":0.2704425436,"remaining_time":2.576321073},
{"learn":[5.348292324],"iteration":95,"passed_time":0.2712383012,"remaining_time":2.55416067},
{"learn":[5.339772295],"iteration":96,"passed_time":0.271944576,"remaining_time":2.531607754},
{"learn":[5.331515983],"iteration":97,"passed_time":0.2726987455,"remaining_time":2.509941515},
{"learn":[5.323861644],"iteration":98,"passed_time":0.2734087236,"remaining_time":2.488295555},
{"learn":[5.313277281],"iteration":99,"passed_time":0.2741591587,"remaining_time":2.467432428},
{"learn":[5.30685627],"iteration":100,"passed_time":0.2749292071,"remaining_time":2.44714215},
{"learn":[5.29652059],"iteration":101,"passed_time":0.2757200824,"remaining_time":2.42741798},
{"learn":[5.288350766],"iteration":102,"passed_time":0.2764761492,"remaining_time":2.407758309},
{"learn":[5.27993346],"iteration":103,"passed_time":0.2772216544,"remaining_time":2.388371176},
{"learn":[5.271789139],"iteration":104,"passed_time":0.2779051769,"remaining_time":2.368810794},
{"learn":[5.262684686],"iteration":105,"passed_time":0.2785926135,"remaining_time":2.349639589},
{"learn":[5.251619772],"iteration":106,"passed_time":0.2794508454,"remaining_time":2.332239298},
{"learn":[5.241012171],"iteration":107,"passed_time":0.2802447431,"remaining_time":2.31461399},
{"learn":[5.232684032],"iteration":108,"passed_time":0.2809681766,"remaining_time":2.296721517},
{"learn":[5.224267141],"iteration":109,"passed_time":0.2816563571,"remaining_time":2.27885598},
{"learn":[5.216324968],"iteration":110,"passed_time":0.2823968261,"remaining_time":2.261718725},
{"learn":[5.211102527],"iteration":111,"passed_time":0.2831744748,"remaining_time":2.24516905},
{"learn":[5.206364257],"iteration":112,"passed_time":0.283908985,"remaining_time":2.228559909},
{"learn":[5.196937641],"iteration":113,"passed_time":0.284633604,"remaining_time":2.212152396},
{"learn":[5.190746047],"iteration":114,"passed_time":0.2853477543,"remaining_time":2.195937066},
{"learn":[5.181885213],"iteration":115,"passed_time":0.2860693519,"remaining_time":2.18004575},
{"learn":[5.178293568],"iteration":116,"passed_time":0.2866259004,"remaining_time":2.16316812},
{"learn":[5.170991438],"iteration":117,"passed_time":0.2873942504,"remaining_time":2.148150244},
{"learn":[5.166257212],"iteration":118,"passed_time":0.2881635089,"remaining_time":2.133378583},
{"learn":[5.161421246],"iteration":119,"passed_time":0.2889220136,"remaining_time":2.118761433},
{"learn":[5.158223542],"iteration":120,"passed_time":0.2896496096,"remaining_time":2.104148817},
{"learn":[5.15470988],"iteration":121,"passed_time":0.2903359543,"remaining_time":2.08946695},
{"learn":[5.146388143],"iteration":122,"passed_time":0.291109981,"remaining_time":2.075637832},
{"learn":[5.139529364],"iteration":123,"passed_time":0.2918230849,"remaining_time":2.06158889},
{"learn":[5.134276023],"iteration":124,"passed_time":0.292622905,"remaining_time":2.048360335},
{"learn":[5.128536065],"iteration":125,"passed_time":0.2933645078,"remaining_time":2.034925237},
{"learn":[5.123300353],"iteration":126,"passed_time":0.2940326599,"remaining_time":2.021185134},
{"learn":[5.116200518],"iteration":127,"passed_time":0.2946903231,"remaining_time":2.007577826},
{"learn":[5.108728704],"iteration":128,"passed_time":0.295465927,"remaining_time":1.994967616},
{"learn":[5.104075866],"iteration":129,"passed_time":0.2961526941,"remaining_time":1.981944953},
{"learn":[5.100317606],"iteration":130,"passed_time":0.2968150177,"remaining_time":1.968948476},
{"learn":[5.095814182],"iteration":131,"passed_time":0.2974775223,"remaining_time":1.956140071},
{"learn":[5.092146915],"iteration":132,"passed_time":0.2983158502,"remaining_time":1.944660467},
{"learn":[5.085258329],"iteration":133,"passed_time":0.2990771362,"remaining_time":1.932841791},
{"learn":[5.079219421],"iteration":134,"passed_time":0.2999466661,"remaining_time":1.92188049},
{"learn":[5.076476829],"iteration":135,"passed_time":0.3008247718,"remaining_time":1.91112208},
{"learn":[5.072133867],"iteration":136,"passed_time":0.3016968492,"remaining_time":1.900469933},
{"learn":[5.067031564],"iteration":137,"passed_time":0.3024118549,"remaining_time":1.888978398},
{"learn":[5.061358312],"iteration":138,"passed_time":0.3033742413,"remaining_time":1.879174257},
{"learn":[5.056759124],"iteration":139,"passed_time":0.3042995777,"remaining_time":1.869268835},
{"learn":[5.050254],"iteration":140,"passed_time":0.3050876501,"remaining_time":1.858654549},
{"learn":[5.048376474],"iteration":141,"passed_time":0.3056142418,"remaining_time":1.846598728},
{"learn":[5.042603751],"iteration":142,"passed_time":0.3063690699,"remaining_time":1.836071978},
{"learn":[5.037477349],"iteration":143,"passed_time":0.3071910698,"remaining_time":1.826080248},
{"learn":[5.03230489],"iteration":144,"passed_time":0.3079290046,"remaining_time":1.815719303},
{"learn":[5.025976187],"iteration":145,"passed_time":0.3087035458,"remaining_time":1.805704302},
{"learn":[5.01952451],"iteration":146,"passed_time":0.3093522796,"remaining_time":1.795084997},
{"learn":[5.017569424],"iteration":147,"passed_time":0.3101062404,"remaining_time":1.785206194},
{"learn":[5.008962367],"iteration":148,"passed_time":0.3108829037,"remaining_time":1.775579537},
{"learn":[5.003880266],"iteration":149,"passed_time":0.31170031,"remaining_time":1.766301756},
{"learn":[4.996387564],"iteration":150,"passed_time":0.3126171953,"remaining_time":1.757695356},
{"learn":[4.993361683],"iteration":151,"passed_time":0.3134533157,"remaining_time":1.74873955},
{"learn":[4.99005752],"iteration":152,"passed_time":0.3143172303,"remaining_time":1.740043752},
{"learn":[4.986908764],"iteration":153,"passed_time":0.3150279763,"remaining_time":1.730608233},
{"learn":[4.985207175],"iteration":154,"passed_time":0.315889837,"remaining_time":1.722109111},
{"learn":[4.979003494],"iteration":155,"passed_time":0.316609077,"remaining_time":1.712936288},
{"learn":[4.973142217],"iteration":156,"passed_time":0.317556119,"remaining_time":1.70509432},
{"learn":[4.967056696],"iteration":157,"passed_time":0.3183596263,"remaining_time":1.696574717},
{"learn":[4.961460696],"iteration":158,"passed_time":0.3191217282,"remaining_time":1.687933166},
{"learn":[4.954240363],"iteration":159,"passed_time":0.3199147545,"remaining_time":1.679552461},
{"learn":[4.952320707],"iteration":160,"passed_time":0.3204532372,"remaining_time":1.66993954},
{"learn":[4.948337777],"iteration":161,"passed_time":0.3211477886,"remaining_time":1.661245968},
{"learn":[4.943228639],"iteration":162,"passed_time":0.3218507046,"remaining_time":1.652693496},
{"learn":[4.938545759],"iteration":163,"passed_time":0.3226894593,"remaining_time":1.644929195},
{"learn":[4.935330572],"iteration":164,"passed_time":0.3233464433,"remaining_time":1.636328971},
{"learn":[4.932051543],"iteration":165,"passed_time":0.3240615669,"remaining_time":1.628116547},
{"learn":[4.928964153],"iteration":166,"passed_time":0.3248080204,"remaining_time":1.620150186},
{"learn":[4.922860227],"iteration":167,"passed_time":0.3254494399,"remaining_time":1.611749607},
{"learn":[4.917668772],"iteration":168,"passed_time":0.32620458,"remaining_time":1.604000036},
{"learn":[4.910365386],"iteration":169,"passed_time":0.3271248217,"remaining_time":1.597138835},
{"learn":[4.906457206],"iteration":170,"passed_time":0.3279743062,"remaining_time":1.590004093},
{"learn":[4.901996508],"iteration":171,"passed_time":0.3287212037,"remaining_time":1.582448585},
{"learn":[4.896816173],"iteration":172,"passed_time":0.3295566257,"remaining_time":1.575394968},
{"learn":[4.891123132],"iteration":173,"passed_time":0.3303775751,"remaining_time":1.568344121},
{"learn":[4.887630202],"iteration":174,"passed_time":0.3311704684,"remaining_time":1.561232208},
{"learn":[4.885259712],"iteration":175,"passed_time":0.3319492363,"remaining_time":1.55412597},
{"learn":[4.880659728],"iteration":176,"passed_time":0.3327296985,"remaining_time":1.547099107},
{"learn":[4.877299723],"iteration":177,"passed_time":0.3334138649,"remaining_time":1.539697736},
{"learn":[4.874038772],"iteration":178,"passed_time":0.3341364461,"remaining_time":1.53254761},
{"learn":[4.86943698],"iteration":179,"passed_time":0.3349416472,"remaining_time":1.525845282},
{"learn":[4.861268711],"iteration":180,"passed_time":0.3358050113,"remaining_time":1.519471294},
{"learn":[4.858673056],"iteration":181,"passed_time":0.3366761888,"remaining_time":1.51319298},
{"learn":[4.854036207],"iteration":182,"passed_time":0.3374375574,"remaining_time":1.506483521},
{"learn":[4.85130244],"iteration":183,"passed_time":0.3382764286,"remaining_time":1.500182423},
{"learn":[4.847510084],"iteration":184,"passed_time":0.3391111629,"remaining_time":1.49392215},
{"learn":[4.845691673],"iteration":185,"passed_time":0.3399302134,"remaining_time":1.487651579},
{"learn":[4.842058646],"iteration":186,"passed_time":0.3408392236,"remaining_time":1.481830421},
{"learn":[4.838623675],"iteration":187,"passed_time":0.3417400004,"remaining_time":1.476025959},
{"learn":[4.834602161],"iteration":188,"passed_time":0.3426089248,"remaining_time":1.470136709},
{"learn":[4.830858976],"iteration":189,"passed_time":0.3434880446,"remaining_time":1.464343769},
{"learn":[4.827590511],"iteration":190,"passed_time":0.3442287951,"remaining_time":1.458016206},
{"learn":[4.822246226],"iteration":191,"passed_time":0.3449777128,"remaining_time":1.451781208},
{"learn":[4.816686395],"iteration":192,"passed_time":0.3456737158,"remaining_time":1.445381806},
{"learn":[4.814797121],"iteration":193,"passed_time":0.3464555366,"remaining_time":1.439397745},
{"learn":[4.811639392],"iteration":194,"passed_time":0.3472244468,"remaining_time":1.433413742},
{"learn":[4.804813432],"iteration":195,"passed_time":0.3479175,"remaining_time":1.427171786},
{"learn":[4.80251613],"iteration":196,"passed_time":0.3487031952,"remaining_time":1.421363786},
{"learn":[4.800087884],"iteration":197,"passed_time":0.3494348069,"remaining_time":1.41538745},
{"learn":[4.794773135],"iteration":198,"passed_time":0.3503591642,"remaining_time":1.410239651},
{"learn":[4.791664833],"iteration":199,"passed_time":0.3511673062,"remaining_time":1.404669225},
{"learn":[4.785989873],"iteration":200,"passed_time":0.3519905759,"remaining_time":1.399206319},
{"learn":[4.782387142],"iteration":201,"passed_time":0.3527969814,"remaining_time":1.393722729},
{"learn":[4.778623704],"iteration":202,"passed_time":0.3534222739,"remaining_time":1.387574149},
{"learn":[4.775772178],"iteration":203,"passed_time":0.3542317426,"remaining_time":1.382198368},
{"learn":[4.77023101],"iteration":204,"passed_time":0.355097476,"remaining_time":1.377085334},
{"learn":[4.764496689],"iteration":205,"passed_time":0.3558489924,"remaining_time":1.371573301},
{"learn":[4.763138716],"iteration":206,"passed_time":0.3565917985,"remaining_time":1.366073895},
{"learn":[4.758053283],"iteration":207,"passed_time":0.3574267998,"remaining_time":1.360971276},
{"learn":[4.755063788],"iteration":208,"passed_time":0.3581774824,"remaining_time":1.355590376},
{"learn":[4.752465267],"iteration":209,"passed_time":0.3589610483,"remaining_time":1.350377277},
{"learn":[4.748067377],"iteration":210,"passed_time":0.3597501872,"remaining_time":1.345227003},
{"learn":[4.744163298],"iteration":211,"passed_time":0.3604091586,"remaining_time":1.339634042},
{"learn":[4.736670896],"iteration":212,"passed_time":0.3611263917,"remaining_time":1.334302677},
{"learn":[4.73349255],"iteration":213,"passed_time":0.3618096965,"remaining_time":1.32888982},
{"learn":[4.731864595],"iteration":214,"passed_time":0.3625546909,"remaining_time":1.323746197},
{"learn":[4.728398311],"iteration":215,"passed_time":0.3633416178,"remaining_time":1.318795502},
{"learn":[4.723865975],"iteration":216,"passed_time":0.364043057,"remaining_time":1.313574717},
{"learn":[4.723483365],"iteration":217,"passed_time":0.3647297078,"remaining_time":1.308342346},
{"learn":[4.72095416],"iteration":218,"passed_time":0.3655334157,"remaining_time":1.303568939},
{"learn":[4.716173382],"iteration":219,"passed_time":0.3663947611,"remaining_time":1.299035971},
{"learn":[4.710563974],"iteration":220,"passed_time":0.3671966633,"remaining_time":1.2943267},
{"learn":[4.707160263],"iteration":221,"passed_time":0.3680261313,"remaining_time":1.289749235},
{"learn":[4.70408351],"iteration":222,"passed_time":0.3687930093,"remaining_time":1.284987301},
{"learn":[4.702501831],"iteration":223,"passed_time":0.369636015,"remaining_time":1.280524766},
{"learn":[4.700269738],"iteration":224,"passed_time":0.3704307263,"remaining_time":1.275928057},
{"learn":[4.695346302],"iteration":225,"passed_time":0.3711779011,"remaining_time":1.271202192},
{"learn":[4.689769299],"iteration":226,"passed_time":0.3720319995,"remaining_time":1.266875487},
{"learn":[4.687919514],"iteration":227,"passed_time":0.3727670795,"remaining_time":1.262176252},
{"learn":[4.682982074],"iteration":228,"passed_time":0.3736771785,"remaining_time":1.258100894},
{"learn":[4.679578702],"iteration":229,"passed_time":0.374420492,"remaining_time":1.253494691},
{"learn":[4.675751423],"iteration":230,"passed_time":0.3752743915,"remaining_time":1.249290074},
{"learn":[4.672710726],"iteration":231,"passed_time":0.3760190688,"remaining_time":1.244752779},
{"learn":[4.6690533],"iteration":232,"passed_time":0.3767298395,"remaining_time":1.240136424},
{"learn":[4.667595702],"iteration":233,"passed_time":0.3774579913,"remaining_time":1.235610348},
{"learn":[4.664241291],"iteration":234,"passed_time":0.3783140764,"remaining_time":1.231533057},
{"learn":[4.662246999],"iteration":235,"passed_time":0.3790583525,"remaining_time":1.227121107},
{"learn":[4.658668443],"iteration":236,"passed_time":0.3797661937,"remaining_time":1.222622809},
{"learn":[4.658017572],"iteration":237,"passed_time":0.3805372216,"remaining_time":1.218358667},
{"learn":[4.657656705],"iteration":238,"passed_time":0.3812832002,"remaining_time":1.214043997},
{"learn":[4.653242871],"iteration":239,"passed_time":0.3821125209,"remaining_time":1.210022983},
{"learn":[4.6507302],"iteration":240,"passed_time":0.3828498417,"remaining_time":1.205738713},
{"learn":[4.647671336],"iteration":241,"passed_time":0.3835885465,"remaining_time":1.201488092},
{"learn":[4.645506007],"iteration":242,"passed_time":0.3843756915,"remaining_time":1.197417278},
{"learn":[4.641297906],"iteration":243,"passed_time":0.3852643019,"remaining_time":1.193687755},
{"learn":[4.63798107],"iteration":244,"passed_time":0.3860096158,"remaining_time":1.189539836},
{"learn":[4.635062318],"iteration":245,"passed_time":0.3867671811,"remaining_time":1.185457132},
{"learn":[4.631606017],"iteration":246,"passed_time":0.3874410276,"remaining_time":1.181146129},
{"learn":[4.630215494],"iteration":247,"passed_time":0.3881379044,"remaining_time":1.176934291},
{"learn":[4.62729814],"iteration":248,"passed_time":0.3888477463,"remaining_time":1.172789789},
{"learn":[4.624691756],"iteration":249,"passed_time":0.389622533,"remaining_time":1.168867599},
{"learn":[4.621840053],"iteration":250,"passed_time":0.3903147301,"remaining_time":1.164724035},
{"learn":[4.619602091],"iteration":251,"passed_time":0.3910058206,"remaining_time":1.160604579},
{"learn":[4.613584029],"iteration":252,"passed_time":0.3917006558,"remaining_time":1.15652328},
{"learn":[4.6119388],"iteration":253,"passed_time":0.3923688052,"remaining_time":1.15239027},
{"learn":[4.60870702],"iteration":254,"passed_time":0.3930274982,"remaining_time":1.148256809},
{"learn":[4.604771557],"iteration":255,"passed_time":0.3937188736,"remaining_time":1.144245476},
{"learn":[4.604231277],"iteration":256,"passed_time":0.3944294389,"remaining_time":1.14031546},
{"learn":[4.600750354],"iteration":257,"passed_time":0.3952317507,"remaining_time":1.13667426},
{"learn":[4.596488253],"iteration":258,"passed_time":0.3959829263,"remaining_time":1.132908681},
{"learn":[4.59470784],"iteration":259,"passed_time":0.3967271332,"remaining_time":1.129146456},
{"learn":[4.588818005],"iteration":260,"passed_time":0.3974362456,"remaining_time":1.125307991},
{"learn":[4.585054174],"iteration":261,"passed_time":0.3981851815,"remaining_time":1.121605588},
{"learn":[4.581471435],"iteration":262,"passed_time":0.3989419744,"remaining_time":1.117947662},
{"learn":[4.577555199],"iteration":263,"passed_time":0.3995938366,"remaining_time":1.114019181},
{"learn":[4.57457145],"iteration":264,"passed_time":0.4002536874,"remaining_time":1.110137586},
{"learn":[4.573029224],"iteration":265,"passed_time":0.4008934167,"remaining_time":1.106224691},
{"learn":[4.571326203],"iteration":266,"passed_time":0.4015252103,"remaining_time":1.102314529},
{"learn":[4.571019224],"iteration":267,"passed_time":0.4021690495,"remaining_time":1.098461732},
{"learn":[4.565766631],"iteration":268,"passed_time":0.4028336163,"remaining_time":1.094689121},
{"learn":[4.563383471],"iteration":269,"passed_time":0.4034982934,"remaining_time":1.09093983},
{"learn":[4.558165805],"iteration":270,"passed_time":0.404154587,"remaining_time":1.087190753},
{"learn":[4.55629209],"iteration":271,"passed_time":0.4047887931,"remaining_time":1.083405299},
{"learn":[4.549383848],"iteration":272,"passed_time":0.4054148429,"remaining_time":1.079621212},
{"learn":[4.546227503],"iteration":273,"passed_time":0.4060830751,"remaining_time":1.075971944},
{"learn":[4.540620977],"iteration":274,"passed_time":0.4067565925,"remaining_time":1.072358289},
{"learn":[4.532898237],"iteration":275,"passed_time":0.4074124582,"remaining_time":1.068719637},
{"learn":[4.529757367],"iteration":276,"passed_time":0.4080898955,"remaining_time":1.065158825},
{"learn":[4.52579294],"iteration":277,"passed_time":0.4087698903,"remaining_time":1.061625399},
{"learn":[4.521572155],"iteration":278,"passed_time":0.4095000371,"remaining_time":1.058242031},
{"learn":[4.518818099],"iteration":279,"passed_time":0.4102402874,"remaining_time":1.054903596},
{"learn":[4.514012334],"iteration":280,"passed_time":0.4109169783,"remaining_time":1.051421023},
{"learn":[4.508331416],"iteration":281,"passed_time":0.411705545,"remaining_time":1.048243196},
{"learn":[4.506038537],"iteration":282,"passed_time":0.4124510242,"remaining_time":1.04497309},
{"learn":[4.505805643],"iteration":283,"passed_time":0.4130856067,"remaining_time":1.041441177},
{"learn":[4.501550352],"iteration":284,"passed_time":0.4138447095,"remaining_time":1.038241991},
{"learn":[4.494692643],"iteration":285,"passed_time":0.4146560124,"remaining_time":1.035190185},
{"learn":[4.489330245],"iteration":286,"passed_time":0.4153635529,"remaining_time":1.031896213},
{"learn":[4.484826955],"iteration":287,"passed_time":0.4161296639,"remaining_time":1.028765002},
{"learn":[4.478285428],"iteration":288,"passed_time":0.4168753289,"remaining_time":1.025599858},
{"learn":[4.475311671],"iteration":289,"passed_time":0.417584637,"remaining_time":1.022362387},
{"learn":[4.471581298],"iteration":290,"passed_time":0.4182887486,"remaining_time":1.019129631},
{"learn":[4.469164956],"iteration":291,"passed_time":0.4189485774,"remaining_time":1.015806825},
{"learn":[4.462068024],"iteration":292,"passed_time":0.419649251,"remaining_time":1.012600753},
{"learn":[4.458540976],"iteration":293,"passed_time":0.4203209442,"remaining_time":1.009342131},
{"learn":[4.455757458],"iteration":294,"passed_time":0.421008988,"remaining_time":1.006140124},
{"learn":[4.453027414],"iteration":295,"passed_time":0.421688619,"remaining_time":1.002935094},
{"learn":[4.450659338],"iteration":296,"passed_time":0.422442575,"remaining_time":0.9999229974},
{"learn":[4.444696901],"iteration":297,"passed_time":0.4231429236,"remaining_time":0.9967997731},
{"learn":[4.442052813],"iteration":298,"passed_time":0.4238533333,"remaining_time":0.9937163432},
{"learn":[4.440036756],"iteration":299,"passed_time":0.4244939461,"remaining_time":0.9904858743},
{"learn":[4.435017051],"iteration":300,"passed_time":0.4252237113,"remaining_time":0.9874796485},
{"learn":[4.429962125],"iteration":301,"passed_time":0.4258866054,"remaining_time":0.9843339423},
{"learn":[4.427666256],"iteration":302,"passed_time":0.4266817366,"remaining_time":0.9815088133},
{"learn":[4.425030004],"iteration":303,"passed_time":0.4273611833,"remaining_time":0.9784321827},
{"learn":[4.422588771],"iteration":304,"passed_time":0.4280769527,"remaining_time":0.9754540398},
{"learn":[4.418936667],"iteration":305,"passed_time":0.4287933033,"remaining_time":0.9724920016},
{"learn":[4.416887976],"iteration":306,"passed_time":0.4294627612,"remaining_time":0.9694387411},
{"learn":[4.413773354],"iteration":307,"passed_time":0.4302067693,"remaining_time":0.9665684556},
{"learn":[4.411129391],"iteration":308,"passed_time":0.430939971,"remaining_time":0.9636877668},
{"learn":[4.40850819],"iteration":309,"passed_time":0.4316005444,"remaining_time":0.9606592763},
{"learn":[4.404880292],"iteration":310,"passed_time":0.4324093783,"remaining_time":0.9579744747},
{"learn":[4.404593827],"iteration":311,"passed_time":0.4330940057,"remaining_time":0.9550278075},
{"learn":[4.402139942],"iteration":312,"passed_time":0.4337945751,"remaining_time":0.952130585},
{"learn":[4.400284725],"iteration":313,"passed_time":0.4344514334,"remaining_time":0.9491518576},
{"learn":[4.395805521],"iteration":314,"passed_time":0.4351984988,"remaining_time":0.946384037},
{"learn":[4.392838833],"iteration":315,"passed_time":0.4358636854,"remaining_time":0.9434517746},
{"learn":[4.389213061],"iteration":316,"passed_time":0.4365742952,"remaining_time":0.9406316834},
{"learn":[4.3861981],"iteration":317,"passed_time":0.4372497763,"remaining_time":0.9377495203},
{"learn":[4.385054234],"iteration":318,"passed_time":0.4380173855,"remaining_time":0.9350778669},
{"learn":[4.379364607],"iteration":319,"passed_time":0.438728595,"remaining_time":0.9322982644},
{"learn":[4.378387619],"iteration":320,"passed_time":0.4393534624,"remaining_time":0.9293489126},
{"learn":[4.375816727],"iteration":321,"passed_time":0.4400547126,"remaining_time":0.9265748297},
{"learn":[4.374600202],"iteration":322,"passed_time":0.4407446622,"remaining_time":0.9237898957},
{"learn":[4.37098897],"iteration":323,"passed_time":0.4414461617,"remaining_time":0.9210419917},
{"learn":[4.367418484],"iteration":324,"passed_time":0.4421115986,"remaining_time":0.9182317816},
{"learn":[4.363584638],"iteration":325,"passed_time":0.4428443251,"remaining_time":0.91557385},
{"learn":[4.360770706],"iteration":326,"passed_time":0.4435547673,"remaining_time":0.91288183},
{"learn":[4.358675808],"iteration":327,"passed_time":0.4442650464,"remaining_time":0.9102015584},
{"learn":[4.354228195],"iteration":328,"passed_time":0.4449543569,"remaining_time":0.9074904969},
{"learn":[4.353773425],"iteration":329,"passed_time":0.4456831227,"remaining_time":0.9048717946},
{"learn":[4.351648009],"iteration":330,"passed_time":0.4464271712,"remaining_time":0.9022954005},
{"learn":[4.348209927],"iteration":331,"passed_time":0.4471287726,"remaining_time":0.8996446388},
{"learn":[4.345852733],"iteration":332,"passed_time":0.4478626997,"remaining_time":0.8970703324},
{"learn":[4.34237339],"iteration":333,"passed_time":0.4486006218,"remaining_time":0.8945150124},
{"learn":[4.340814362],"iteration":334,"passed_time":0.4494267497,"remaining_time":0.8921456375},
{"learn":[4.339707068],"iteration":335,"passed_time":0.4501263911,"remaining_time":0.8895354872},
{"learn":[4.335430786],"iteration":336,"passed_time":0.450828398,"remaining_time":0.886941329},
{"learn":[4.33521887],"iteration":337,"passed_time":0.4515166313,"remaining_time":0.8843313904},
{"learn":[4.328507238],"iteration":338,"passed_time":0.4522713762,"remaining_time":0.8818624768},
{"learn":[4.326140732],"iteration":339,"passed_time":0.4529361548,"remaining_time":0.8792290063},
{"learn":[4.323785636],"iteration":340,"passed_time":0.4536261678,"remaining_time":0.8766558491},
{"learn":[4.320632534],"iteration":341,"passed_time":0.4543062987,"remaining_time":0.8740746916},
{"learn":[4.31973724],"iteration":342,"passed_time":0.4549672242,"remaining_time":0.8714678318},
{"learn":[4.318000924],"iteration":343,"passed_time":0.4557386899,"remaining_time":0.869083083},
{"learn":[4.312713628],"iteration":344,"passed_time":0.4565539233,"remaining_time":0.866790782},
{"learn":[4.308220789],"iteration":345,"passed_time":0.4572676434,"remaining_time":0.8643151409},
{"learn":[4.305890947],"iteration":346,"passed_time":0.4579443511,"remaining_time":0.8617800037},
{"learn":[4.305137856],"iteration":347,"passed_time":0.4586018665,"remaining_time":0.859219589},
{"learn":[4.304787172],"iteration":348,"passed_time":0.4592941388,"remaining_time":0.8567349121},
{"learn":[4.30350134],"iteration":349,"passed_time":0.4600136122,"remaining_time":0.854310994},
{"learn":[4.30293809],"iteration":350,"passed_time":0.460664511,"remaining_time":0.8517699932},
{"learn":[4.299548459],"iteration":351,"passed_time":0.4613490092,"remaining_time":0.8493015851},
{"learn":[4.294768408],"iteration":352,"passed_time":0.4620060374,"remaining_time":0.8467929355},
{"learn":[4.294581479],"iteration":353,"passed_time":0.4626780508,"remaining_time":0.8443220927},
{"learn":[4.292551604],"iteration":354,"passed_time":0.4634019419,"remaining_time":0.841955641},
{"learn":[4.288628894],"iteration":355,"passed_time":0.4640614842,"remaining_time":0.8394820107},
{"learn":[4.287802767],"iteration":356,"passed_time":0.4647180973,"remaining_time":0.8370132676},
{"learn":[4.284566905],"iteration":357,"passed_time":0.4654444365,"remaining_time":0.8346796879},
{"learn":[4.27890232],"iteration":358,"passed_time":0.4661567181,"remaining_time":0.8323299618},
{"learn":[4.276938023],"iteration":359,"passed_time":0.4668535688,"remaining_time":0.8299619001},
{"learn":[4.273425094],"iteration":360,"passed_time":0.4675524703,"remaining_time":0.8276067273},
{"learn":[4.269726505],"iteration":361,"passed_time":0.4681978876,"remaining_time":0.8251664428},
{"learn":[4.265565857],"iteration":362,"passed_time":0.4689688846,"remaining_time":0.8229564174},
{"learn":[4.262117173],"iteration":363,"passed_time":0.4696926962,"remaining_time":0.8206718538},
{"learn":[4.259185148],"iteration":364,"passed_time":0.4703601002,"remaining_time":0.8182977086},
{"learn":[4.257668507],"iteration":365,"passed_time":0.4711180721,"remaining_time":0.8160897752},
{"learn":[4.253432436],"iteration":366,"passed_time":0.4719241911,"remaining_time":0.8139727873},
{"learn":[4.250216667],"iteration":367,"passed_time":0.4726590613,"remaining_time":0.8117405618},
{"learn":[4.24514828],"iteration":368,"passed_time":0.473467541,"remaining_time":0.8096423262},
{"learn":[4.244015772],"iteration":369,"passed_time":0.474212511,"remaining_time":0.8074429242},
{"learn":[4.240329192],"iteration":370,"passed_time":0.4750838089,"remaining_time":0.8054655412},
{"learn":[4.236718014],"iteration":371,"passed_time":0.4757711731,"remaining_time":0.8031835933},
{"learn":[4.233495944],"iteration":372,"passed_time":0.4764974353,"remaining_time":0.8009755815},
{"learn":[4.230357491],"iteration":373,"passed_time":0.4772605623,"remaining_time":0.7988371978},
{"learn":[4.227381215],"iteration":374,"passed_time":0.4779627958,"remaining_time":0.7966046596},
{"learn":[4.226169067],"iteration":375,"passed_time":0.478731019,"remaining_time":0.7944897762},
{"learn":[4.225963861],"iteration":376,"passed_time":0.4794122603,"remaining_time":0.7922382975},
{"learn":[4.224346548],"iteration":377,"passed_time":0.4801583912,"remaining_time":0.7901019029},
{"learn":[4.222595381],"iteration":378,"passed_time":0.4808985835,"remaining_time":0.7879631144},
{"learn":[4.219700938],"iteration":379,"passed_time":0.481558003,"remaining_time":0.7856998997},
{"learn":[4.216356207],"iteration":380,"passed_time":0.4823321829,"remaining_time":0.7836315517},
{"learn":[4.214326494],"iteration":381,"passed_time":0.4830952321,"remaining_time":0.7815519723},
{"learn":[4.212901398],"iteration":382,"passed_time":0.4838123581,"remaining_time":0.7794052871},
{"learn":[4.211331091],"iteration":383,"passed_time":0.4846314048,"remaining_time":0.7774295453},
{"learn":[4.208624791],"iteration":384,"passed_time":0.4854566938,"remaining_time":0.7754697836},
{"learn":[4.204659106],"iteration":385,"passed_time":0.4862712848,"remaining_time":0.7734988831},
{"learn":[4.202968852],"iteration":386,"passed_time":0.4873442405,"remaining_time":0.7719432026},
{"learn":[4.197261935],"iteration":387,"passed_time":0.4880281123,"remaining_time":0.7697763009},
{"learn":[4.196934403],"iteration":388,"passed_time":0.4887726953,"remaining_time":0.7677123826},
{"learn":[4.192479929],"iteration":389,"passed_time":0.4896247124,"remaining_time":0.7658232681},
{"learn":[4.190243116],"iteration":390,"passed_time":0.4903513372,"remaining_time":0.7637441544},
{"learn":[4.185852431],"iteration":391,"passed_time":0.4911224484,"remaining_time":0.7617409404},
{"learn":[4.180967944],"iteration":392,"passed_time":0.4918861147,"remaining_time":0.7597324978},
{"learn":[4.178283162],"iteration":393,"passed_time":0.4926480113,"remaining_time":0.7577276519},
{"learn":[4.176341157],"iteration":394,"passed_time":0.4934528642,"remaining_time":0.7557948932},
{"learn":[4.176041504],"iteration":395,"passed_time":0.4941637343,"remaining_time":0.7537244836},
{"learn":[4.175564513],"iteration":396,"passed_time":0.4949601305,"remaining_time":0.751790828},
{"learn":[4.170830274],"iteration":397,"passed_time":0.4957189286,"remaining_time":0.7498060177},
{"learn":[4.167804808],"iteration":398,"passed_time":0.4964148808,"remaining_time":0.7477326901},
{"learn":[4.165860548],"iteration":399,"passed_time":0.4970634148,"remaining_time":0.7455951221},
{"learn":[4.160950571],"iteration":400,"passed_time":0.4977606505,"remaining_time":0.7435377298},
{"learn":[4.158544115],"iteration":401,"passed_time":0.4984539872,"remaining_time":0.7414813044},
{"learn":[4.154448767],"iteration":402,"passed_time":0.4991851148,"remaining_time":0.7394876266},
{"learn":[4.15197457],"iteration":403,"passed_time":0.4998472941,"remaining_time":0.7373984833},
{"learn":[4.149562679],"iteration":404,"passed_time":0.5005206585,"remaining_time":0.7353328193},
{"learn":[4.149327961],"iteration":405,"passed_time":0.5012395704,"remaining_time":0.7333406523},
{"learn":[4.147444889],"iteration":406,"passed_time":0.501955117,"remaining_time":0.7313498388},
{"learn":[4.147254809],"iteration":407,"passed_time":0.5026599471,"remaining_time":0.7293497272},
{"learn":[4.144589165],"iteration":408,"passed_time":0.5035194499,"remaining_time":0.7275794496},
{"learn":[4.141691034],"iteration":409,"passed_time":0.5042762983,"remaining_time":0.7256658927},
{"learn":[4.138893468],"iteration":410,"passed_time":0.5051230711,"remaining_time":0.7238868342},
{"learn":[4.136964597],"iteration":411,"passed_time":0.5058917403,"remaining_time":0.7220008332},
{"learn":[4.133773523],"iteration":412,"passed_time":0.5066667063,"remaining_time":0.7201291927},
{"learn":[4.131363444],"iteration":413,"passed_time":0.5074814645,"remaining_time":0.7183191744},
{"learn":[4.130228592],"iteration":414,"passed_time":0.508204405,"remaining_time":0.7163845227},
{"learn":[4.12884186],"iteration":415,"passed_time":0.5089584535,"remaining_time":0.7144993674},
{"learn":[4.12413494],"iteration":416,"passed_time":0.5096503157,"remaining_time":0.7125326956},
{"learn":[4.119422508],"iteration":417,"passed_time":0.5104734983,"remaining_time":0.7107549666},
{"learn":[4.117038244],"iteration":418,"passed_time":0.5111716741,"remaining_time":0.708808455},
{"learn":[4.116067631],"iteration":419,"passed_time":0.511907384,"remaining_time":0.7069197207},
{"learn":[4.110343455],"iteration":420,"passed_time":0.5128388002,"remaining_time":0.7053056183},
{"learn":[4.105604544],"iteration":421,"passed_time":0.5135879932,"remaining_time":0.703445166},
{"learn":[4.103390131],"iteration":422,"passed_time":0.5142874919,"remaining_time":0.7015221817},
{"learn":[4.096724402],"iteration":423,"passed_time":0.5150758931,"remaining_time":0.6997257415},
{"learn":[4.093431279],"iteration":424,"passed_time":0.5158410973,"remaining_time":0.697902661},
{"learn":[4.091412744],"iteration":425,"passed_time":0.5166675659,"remaining_time":0.6961670959},
{"learn":[4.091192901],"iteration":426,"passed_time":0.5174615384,"remaining_time":0.6943921815},
{"learn":[4.088994581],"iteration":427,"passed_time":0.51832876,"remaining_time":0.6927197447},
{"learn":[4.087845355],"iteration":428,"passed_time":0.5191592367,"remaining_time":0.6910021542},
{"learn":[4.083650279],"iteration":429,"passed_time":0.519844051,"remaining_time":0.6890956025},
{"learn":[4.079840652],"iteration":430,"passed_time":0.5205803028,"remaining_time":0.6872626272},
{"learn":[4.075707828],"iteration":431,"passed_time":0.5213700962,"remaining_time":0.6855051265},
{"learn":[4.071345409],"iteration":432,"passed_time":0.5221191398,"remaining_time":0.683698735},
{"learn":[4.067460475],"iteration":433,"passed_time":0.5228345733,"remaining_time":0.6818533836},
{"learn":[4.064914749],"iteration":434,"passed_time":0.5235094856,"remaining_time":0.6799605962},
{"learn":[4.063823175],"iteration":435,"passed_time":0.524243662,"remaining_time":0.6781500582},
{"learn":[4.058898471],"iteration":436,"passed_time":0.5250191384,"remaining_time":0.6763976543},
{"learn":[4.054120355],"iteration":437,"passed_time":0.5258115092,"remaining_time":0.6746713885},
{"learn":[4.052715901],"iteration":438,"passed_time":0.5266299728,"remaining_time":0.6729827215},
{"learn":[4.052114167],"iteration":439,"passed_time":0.5273358396,"remaining_time":0.6711547049},
{"learn":[4.051377267],"iteration":440,"passed_time":0.5280839355,"remaining_time":0.6693853061},
{"learn":[4.049275336],"iteration":441,"passed_time":0.5288570753,"remaining_time":0.6676521448},
{"learn":[4.047099198],"iteration":442,"passed_time":0.5295542332,"remaining_time":0.665827783},
{"learn":[4.044348685],"iteration":443,"passed_time":0.5303113699,"remaining_time":0.6640836074},
{"learn":[4.042822379],"iteration":444,"passed_time":0.5310719205,"remaining_time":0.6623481256},
{"learn":[4.041258611],"iteration":445,"passed_time":0.5318843383,"remaining_time":0.6606814427},
{"learn":[4.040044254],"iteration":446,"passed_time":0.532601103,"remaining_time":0.658900246},
{"learn":[4.036860137],"iteration":447,"passed_time":0.5334450008,"remaining_time":0.6572804474},
{"learn":[4.036372284],"iteration":448,"passed_time":0.5342205407,"remaining_time":0.6555802181},
{"learn":[4.03368231],"iteration":449,"passed_time":0.5349648816,"remaining_time":0.6538459664},
{"learn":[4.032439519],"iteration":450,"passed_time":0.5357242533,"remaining_time":0.6521344014},
{"learn":[4.032008634],"iteration":451,"passed_time":0.5366873364,"remaining_time":0.6506740273},
{"learn":[4.030034932],"iteration":452,"passed_time":0.5374592282,"remaining_time":0.6489849841},
{"learn":[4.028173412],"iteration":453,"passed_time":0.5382666067,"remaining_time":0.6473426591},
{"learn":[4.023806097],"iteration":454,"passed_time":0.539142725,"remaining_time":0.645786341},
{"learn":[4.020239186],"iteration":455,"passed_time":0.539972996,"remaining_time":0.644178311},
{"learn":[4.017384838],"iteration":456,"passed_time":0.5407042655,"remaining_time":0.6424560529},
{"learn":[4.016468229],"iteration":457,"passed_time":0.5415064289,"remaining_time":0.6408220185},
{"learn":[4.014530169],"iteration":458,"passed_time":0.5423089564,"remaining_time":0.6391920379},
{"learn":[4.012884822],"iteration":459,"passed_time":0.5430211597,"remaining_time":0.6374596223},
{"learn":[4.008924707],"iteration":460,"passed_time":0.5439764088,"remaining_time":0.6360158011},
{"learn":[4.008286778],"iteration":461,"passed_time":0.5447692787,"remaining_time":0.6343850042},
{"learn":[4.006444202],"iteration":462,"passed_time":0.54554534,"remaining_time":0.6327383317},
{"learn":[4.003284363],"iteration":463,"passed_time":0.5462626268,"remaining_time":0.6310275172},
{"learn":[3.999811484],"iteration":464,"passed_time":0.547014796,"remaining_time":0.6293611093},
{"learn":[3.997483319],"iteration":465,"passed_time":0.5479463448,"remaining_time":0.6279041806},
{"learn":[3.99708333],"iteration":466,"passed_time":0.548775395,"remaining_time":0.6263325172},
{"learn":[3.995860263],"iteration":467,"passed_time":0.5494927737,"remaining_time":0.6246370847},
{"learn":[3.994131111],"iteration":468,"passed_time":0.5503831782,"remaining_time":0.623141722},
{"learn":[3.993125499],"iteration":469,"passed_time":0.5512200877,"remaining_time":0.6215886096},
{"learn":[3.992954084],"iteration":470,"passed_time":0.5518895402,"remaining_time":0.6198504602},
{"learn":[3.990635743],"iteration":471,"passed_time":0.5527341853,"remaining_time":0.6183128175},
{"learn":[3.986678254],"iteration":472,"passed_time":0.553646148,"remaining_time":0.6168531078},
{"learn":[3.986393291],"iteration":473,"passed_time":0.554390265,"remaining_time":0.6152094502},
{"learn":[3.986152671],"iteration":474,"passed_time":0.5550718574,"remaining_time":0.613500474},
{"learn":[3.985596662],"iteration":475,"passed_time":0.5559491921,"remaining_time":0.6120112956},
{"learn":[3.983853457],"iteration":476,"passed_time":0.55685955,"remaining_time":0.6105608902},
{"learn":[3.983263928],"iteration":477,"passed_time":0.557553847,"remaining_time":0.6088767952},
{"learn":[3.980067202],"iteration":478,"passed_time":0.5582984135,"remaining_time":0.6072515103},
{"learn":[3.978115407],"iteration":479,"passed_time":0.5592654587,"remaining_time":0.6058709135},
{"learn":[3.972661644],"iteration":480,"passed_time":0.5600857872,"remaining_time":0.6043337288},
{"learn":[3.969938254],"iteration":481,"passed_time":0.560810569,"remaining_time":0.6026968356},
{"learn":[3.968211434],"iteration":482,"passed_time":0.5615872173,"remaining_time":0.6011192367},
{"learn":[3.966113368],"iteration":483,"passed_time":0.5623852958,"remaining_time":0.5995677947},
{"learn":[3.962246044],"iteration":484,"passed_time":0.5631735557,"remaining_time":0.5980090334},
{"learn":[3.961319703],"iteration":485,"passed_time":0.563917969,"remaining_time":0.5964070701},
{"learn":[3.96078191],"iteration":486,"passed_time":0.5645633451,"remaining_time":0.594704304},
{"learn":[3.958913633],"iteration":487,"passed_time":0.5652983364,"remaining_time":0.5930998939},
{"learn":[3.957428286],"iteration":488,"passed_time":0.5659493168,"remaining_time":0.5914112493},
{"learn":[3.952641965],"iteration":489,"passed_time":0.5666978266,"remaining_time":0.5898283501},
{"learn":[3.951486786],"iteration":490,"passed_time":0.5674817366,"remaining_time":0.5882855477},
{"learn":[3.94938344],"iteration":491,"passed_time":0.5681886624,"remaining_time":0.5866663425},
{"learn":[3.947297924],"iteration":492,"passed_time":0.5688492534,"remaining_time":0.5850031876},
{"learn":[3.946284886],"iteration":493,"passed_time":0.5695625086,"remaining_time":0.5833980351},
{"learn":[3.943288204],"iteration":494,"passed_time":0.5702642864,"remaining_time":0.5817847771},
{"learn":[3.943076488],"iteration":495,"passed_time":0.5710410828,"remaining_time":0.5802514228},
{"learn":[3.942347078],"iteration":496,"passed_time":0.5717200995,"remaining_time":0.578622153},
{"learn":[3.940251541],"iteration":497,"passed_time":0.5723640755,"remaining_time":0.5769613773},
{"learn":[3.939011019],"iteration":498,"passed_time":0.5731183609,"remaining_time":0.5754154285},
{"learn":[3.938760512],"iteration":499,"passed_time":0.5737401151,"remaining_time":0.5737401151},
{"learn":[3.934522727],"iteration":500,"passed_time":0.5744374067,"remaining_time":0.5721442434},
{"learn":[3.930091193],"iteration":501,"passed_time":0.5751066075,"remaining_time":0.5705240847},
{"learn":[3.927671752],"iteration":502,"passed_time":0.5758814126,"remaining_time":0.5690120518},
{"learn":[3.927280041],"iteration":503,"passed_time":0.5766136242,"remaining_time":0.567461027},
{"learn":[3.925987561],"iteration":504,"passed_time":0.577364902,"remaining_time":0.5659319337},
{"learn":[3.921645957],"iteration":505,"passed_time":0.5780804802,"remaining_time":0.5643710617},
{"learn":[3.920333743],"iteration":506,"passed_time":0.5787775877,"remaining_time":0.5627955636},
{"learn":[3.918659461],"iteration":507,"passed_time":0.5794602837,"remaining_time":0.5612095661},
{"learn":[3.916124385],"iteration":508,"passed_time":0.5802081074,"remaining_time":0.5596899425},
{"learn":[3.913849268],"iteration":509,"passed_time":0.5809166994,"remaining_time":0.5581356524},
{"learn":[3.912826119],"iteration":510,"passed_time":0.5816830624,"remaining_time":0.556639956},
{"learn":[3.910034145],"iteration":511,"passed_time":0.5823626564,"remaining_time":0.5550644069},
{"learn":[3.90792379],"iteration":512,"passed_time":0.5831196042,"remaining_time":0.5535657841},
{"learn":[3.907823851],"iteration":513,"passed_time":0.5838662548,"remaining_time":0.552060311},
{"learn":[3.904527401],"iteration":514,"passed_time":0.5846064174,"remaining_time":0.5505516746},
{"learn":[3.903378283],"iteration":515,"passed_time":0.5852968582,"remaining_time":0.5489993786},
{"learn":[3.902170135],"iteration":516,"passed_time":0.5860327206,"remaining_time":0.5474928512},
{"learn":[3.899435429],"iteration":517,"passed_time":0.5867830151,"remaining_time":0.5460027284},
{"learn":[3.897497505],"iteration":518,"passed_time":0.5874938544,"remaining_time":0.5444788901},
{"learn":[3.896426119],"iteration":519,"passed_time":0.5882271133,"remaining_time":0.5429788738},
{"learn":[3.896044669],"iteration":520,"passed_time":0.5888412203,"remaining_time":0.5413722543},
{"learn":[3.892795942],"iteration":521,"passed_time":0.5894871429,"remaining_time":0.5397985715},
{"learn":[3.892413888],"iteration":522,"passed_time":0.5901715527,"remaining_time":0.5382635385},
{"learn":[3.891738985],"iteration":523,"passed_time":0.5908597912,"remaining_time":0.5367352301},
{"learn":[3.88822057],"iteration":524,"passed_time":0.5916373572,"remaining_time":0.5352909422},
{"learn":[3.883837053],"iteration":525,"passed_time":0.5923991831,"remaining_time":0.5338350053},
{"learn":[3.881769742],"iteration":526,"passed_time":0.5932303424,"remaining_time":0.5324439316},
{"learn":[3.880356898],"iteration":527,"passed_time":0.5940188567,"remaining_time":0.5310168567},
{"learn":[3.879250273],"iteration":528,"passed_time":0.5947716504,"remaining_time":0.529560392},
{"learn":[3.877174493],"iteration":529,"passed_time":0.5955104427,"remaining_time":0.5280941661},
{"learn":[3.875854201],"iteration":530,"passed_time":0.5961635153,"remaining_time":0.5265549693},
{"learn":[3.873189396],"iteration":531,"passed_time":0.5968113095,"remaining_time":0.5250144602},
{"learn":[3.871583368],"iteration":532,"passed_time":0.597589317,"remaining_time":0.5235913903},
{"learn":[3.869622679],"iteration":533,"passed_time":0.5982594051,"remaining_time":0.5220765595},
{"learn":[3.866860164],"iteration":534,"passed_time":0.5989927617,"remaining_time":0.520619877},
{"learn":[3.864498444],"iteration":535,"passed_time":0.5996601037,"remaining_time":0.5191087465},
{"learn":[3.861416322],"iteration":536,"passed_time":0.6003762379,"remaining_time":0.5176428271},
{"learn":[3.860265769],"iteration":537,"passed_time":0.6010603268,"remaining_time":0.5161521766},
{"learn":[3.859328725],"iteration":538,"passed_time":0.6017438181,"remaining_time":0.5146640077},
{"learn":[3.858521278],"iteration":539,"passed_time":0.6025459829,"remaining_time":0.5132799113},
{"learn":[3.85599111],"iteration":540,"passed_time":0.6032704966,"remaining_time":0.5118320849},
{"learn":[3.852379816],"iteration":541,"passed_time":0.6040033997,"remaining_time":0.5103940167},
{"learn":[3.851327537],"iteration":542,"passed_time":0.604714206,"remaining_time":0.5089399487},
{"learn":[3.847854898],"iteration":543,"passed_time":0.6054873286,"remaining_time":0.5075408489},
{"learn":[3.847083414],"iteration":544,"passed_time":0.6062650115,"remaining_time":0.5061478536},
{"learn":[3.845397429],"iteration":545,"passed_time":0.6069218111,"remaining_time":0.5046565975},
{"learn":[3.841933528],"iteration":546,"passed_time":0.6076085966,"remaining_time":0.5031932254},
{"learn":[3.840996474],"iteration":547,"passed_time":0.6085777509,"remaining_time":0.5019655902},
{"learn":[3.838355966],"iteration":548,"passed_time":0.6093012995,"remaining_time":0.5005371331},
{"learn":[3.83342799],"iteration":549,"passed_time":0.6100226438,"remaining_time":0.4991094358},
{"learn":[3.828161535],"iteration":550,"passed_time":0.6106850346,"remaining_time":0.4976362623},
{"learn":[3.823502399],"iteration":551,"passed_time":0.611461162,"remaining_time":0.4962583344},
{"learn":[3.820068862],"iteration":552,"passed_time":0.6122933735,"remaining_time":0.4949279167},
{"learn":[3.817951642],"iteration":553,"passed_time":0.6129656817,"remaining_time":0.4934705668},
{"learn":[3.815785958],"iteration":554,"passed_time":0.6136165527,"remaining_time":0.4919988576},
{"learn":[3.81503012],"iteration":555,"passed_time":0.6143102062,"remaining_time":0.4905642654},
{"learn":[3.813529315],"iteration":556,"passed_time":0.615023618,"remaining_time":0.4891480481},
{"learn":[3.808881326],"iteration":557,"passed_time":0.6157252063,"remaining_time":0.4877249842},
{"learn":[3.808740434],"iteration":558,"passed_time":0.6164118493,"remaining_time":0.4862927112},
{"learn":[3.80714352],"iteration":559,"passed_time":0.6171375382,"remaining_time":0.48489378},
{"learn":[3.80573346],"iteration":560,"passed_time":0.6178324564,"remaining_time":0.48347317},
{"learn":[3.803370052],"iteration":561,"passed_time":0.6184908608,"remaining_time":0.4820266851},
{"learn":[3.803215211],"iteration":562,"passed_time":0.6191148004,"remaining_time":0.4805562483},
{"learn":[3.801309667],"iteration":563,"passed_time":0.6197530992,"remaining_time":0.4790999136},
{"learn":[3.800003847],"iteration":564,"passed_time":0.6204720944,"remaining_time":0.4777086036},
{"learn":[3.798026138],"iteration":565,"passed_time":0.6211456704,"remaining_time":0.4762848426},
{"learn":[3.794745847],"iteration":566,"passed_time":0.6219414262,"remaining_time":0.4749570327},
{"learn":[3.794312041],"iteration":567,"passed_time":0.622654762,"remaining_time":0.4735684105},
{"learn":[3.792205926],"iteration":568,"passed_time":0.6233904608,"remaining_time":0.4721991013},
{"learn":[3.788991061],"iteration":569,"passed_time":0.6241746647,"remaining_time":0.4708686067},
{"learn":[3.787391572],"iteration":570,"passed_time":0.6248658221,"remaining_time":0.4694701185},
{"learn":[3.7826445],"iteration":571,"passed_time":0.6255892682,"remaining_time":0.4680982636},
{"learn":[3.781700331],"iteration":572,"passed_time":0.6263650984,"remaining_time":0.4667677086},
{"learn":[3.780045374],"iteration":573,"passed_time":0.627128933,"remaining_time":0.4654301838},
{"learn":[3.775462644],"iteration":574,"passed_time":0.6278160381,"remaining_time":0.4640379412},
{"learn":[3.773711943],"iteration":575,"passed_time":0.6285865189,"remaining_time":0.4627095208},
{"learn":[3.772415806],"iteration":576,"passed_time":0.6293212249,"remaining_time":0.4613568079},
{"learn":[3.770170875],"iteration":577,"passed_time":0.6301300111,"remaining_time":0.4600603195},
{"learn":[3.765166479],"iteration":578,"passed_time":0.6308470634,"remaining_time":0.4586988147},
{"learn":[3.763976102],"iteration":579,"passed_time":0.6317527701,"remaining_time":0.4574761438},
{"learn":[3.760761708],"iteration":580,"passed_time":0.6324796726,"remaining_time":0.4561256159},
{"learn":[3.758155662],"iteration":581,"passed_time":0.6333622537,"remaining_time":0.4548890413},
{"learn":[3.756844548],"iteration":582,"passed_time":0.6340438591,"remaining_time":0.4535099301},
{"learn":[3.753098923],"iteration":583,"passed_time":0.6348607175,"remaining_time":0.4522295522},
{"learn":[3.751618946],"iteration":584,"passed_time":0.6355864791,"remaining_time":0.4508861348},
{"learn":[3.751398464],"iteration":585,"passed_time":0.6362878041,"remaining_time":0.4495275613},
{"learn":[3.749920103],"iteration":586,"passed_time":0.6369646062,"remaining_time":0.4481539733},
{"learn":[3.748237465],"iteration":587,"passed_time":0.6376937988,"remaining_time":0.4468194645},
{"learn":[3.746021536],"iteration":588,"passed_time":0.638458437,"remaining_time":0.4455117447},
{"learn":[3.74417648],"iteration":589,"passed_time":0.6392278385,"remaining_time":0.4442091759},
{"learn":[3.738788389],"iteration":590,"passed_time":0.6399043203,"remaining_time":0.4428441066},
{"learn":[3.736021611],"iteration":591,"passed_time":0.6406680205,"remaining_time":0.4415414736},
{"learn":[3.734546151],"iteration":592,"passed_time":0.6414504983,"remaining_time":0.440253546},
{"learn":[3.733527479],"iteration":593,"passed_time":0.6422783821,"remaining_time":0.4389983555},
{"learn":[3.733026392],"iteration":594,"passed_time":0.6431410687,"remaining_time":0.4377682905},
{"learn":[3.730314752],"iteration":595,"passed_time":0.6439139654,"remaining_time":0.436478594},
{"learn":[3.727342596],"iteration":596,"passed_time":0.6446003132,"remaining_time":0.4351322047},
{"learn":[3.725459604],"iteration":597,"passed_time":0.6453169534,"remaining_time":0.4338083868},
{"learn":[3.723158842],"iteration":598,"passed_time":0.6460538306,"remaining_time":0.4325001437},
{"learn":[3.722362756],"iteration":599,"passed_time":0.6466936104,"remaining_time":0.4311290736},
{"learn":[3.721443615],"iteration":600,"passed_time":0.6473439398,"remaining_time":0.4297674409},
{"learn":[3.720743486],"iteration":601,"passed_time":0.6480688391,"remaining_time":0.4284574717},
{"learn":[3.720215334],"iteration":602,"passed_time":0.6487622119,"remaining_time":0.4271286868},
{"learn":[3.719436563],"iteration":603,"passed_time":0.6495011553,"remaining_time":0.4258318833},
{"learn":[3.715046574],"iteration":604,"passed_time":0.6501999955,"remaining_time":0.4245107408},
{"learn":[3.71443396],"iteration":605,"passed_time":0.6509029925,"remaining_time":0.4231943548},
{"learn":[3.712938941],"iteration":606,"passed_time":0.6515638248,"remaining_time":0.4218526905},
{"learn":[3.712814764],"iteration":607,"passed_time":0.6522045227,"remaining_time":0.4205002843},
{"learn":[3.71235348],"iteration":608,"passed_time":0.652997731,"remaining_time":0.4192481327},
{"learn":[3.711223749],"iteration":609,"passed_time":0.6537458533,"remaining_time":0.4179686603},
{"learn":[3.710755648],"iteration":610,"passed_time":0.6543590919,"remaining_time":0.4166050519},
{"learn":[3.708668039],"iteration":611,"passed_time":0.6551485513,"remaining_time":0.4153556175},
{"learn":[3.705623591],"iteration":612,"passed_time":0.6559124723,"remaining_time":0.4140915608},
{"learn":[3.704045802],"iteration":613,"passed_time":0.6566505631,"remaining_time":0.4128128947},
{"learn":[3.699915209],"iteration":614,"passed_time":0.6573046979,"remaining_time":0.4114834288},
{"learn":[3.696182221],"iteration":615,"passed_time":0.6579622175,"remaining_time":0.4101582654},
{"learn":[3.694263278],"iteration":616,"passed_time":0.6586396091,"remaining_time":0.4088476018},
{"learn":[3.693810229],"iteration":617,"passed_time":0.659402321,"remaining_time":0.4075917259},
{"learn":[3.690900932],"iteration":618,"passed_time":0.6601105585,"remaining_time":0.406303914},
{"learn":[3.688020895],"iteration":619,"passed_time":0.6607460604,"remaining_time":0.4049733919},
{"learn":[3.685491894],"iteration":620,"passed_time":0.6614374992,"remaining_time":0.4036792467},
{"learn":[3.684328128],"iteration":621,"passed_time":0.6621583992,"remaining_time":0.4024049435},
{"learn":[3.680640153],"iteration":622,"passed_time":0.6628707427,"remaining_time":0.4011272392},
{"learn":[3.678932783],"iteration":623,"passed_time":0.6635683875,"remaining_time":0.3998424899},
{"learn":[3.674167041],"iteration":624,"passed_time":0.6643013399,"remaining_time":0.398580804},
{"learn":[3.672200976],"iteration":625,"passed_time":0.6650003954,"remaining_time":0.3973005557},
{"learn":[3.670606604],"iteration":626,"passed_time":0.66579146,"remaining_time":0.3960768973},
{"learn":[3.665506042],"iteration":627,"passed_time":0.6664901802,"remaining_time":0.3947999156},
{"learn":[3.664214007],"iteration":628,"passed_time":0.6671632563,"remaining_time":0.3935096472},
{"learn":[3.66261643],"iteration":629,"passed_time":0.6677718135,"remaining_time":0.392183446},
{"learn":[3.662118449],"iteration":630,"passed_time":0.6685148528,"remaining_time":0.3909381627},
{"learn":[3.660871366],"iteration":631,"passed_time":0.6692176588,"remaining_time":0.3896710418},
{"learn":[3.656695243],"iteration":632,"passed_time":0.6699810073,"remaining_time":0.3884408052},
{"learn":[3.654497801],"iteration":633,"passed_time":0.6706568593,"remaining_time":0.3871615308},
{"learn":[3.654189134],"iteration":634,"passed_time":0.6713833374,"remaining_time":0.3859132569},
{"learn":[3.653957699],"iteration":635,"passed_time":0.6720594726,"remaining_time":0.3846378114},
{"learn":[3.651920725],"iteration":636,"passed_time":0.6727410403,"remaining_time":0.3833673432},
{"learn":[3.65106705],"iteration":637,"passed_time":0.6734574849,"remaining_time":0.3821185102},
{"learn":[3.650612844],"iteration":638,"passed_time":0.6741314661,"remaining_time":0.3808473541},
{"learn":[3.649884732],"iteration":639,"passed_time":0.6748031891,"remaining_time":0.3795767938},
{"learn":[3.646276182],"iteration":640,"passed_time":0.6755193758,"remaining_time":0.3783330045},
{"learn":[3.645808194],"iteration":641,"passed_time":0.6761625376,"remaining_time":0.3770501378},
{"learn":[3.645042989],"iteration":642,"passed_time":0.676833217,"remaining_time":0.3757845388},
{"learn":[3.639864499],"iteration":643,"passed_time":0.6775862195,"remaining_time":0.3745662953},
{"learn":[3.637318478],"iteration":644,"passed_time":0.6782450429,"remaining_time":0.3732976592},
{"learn":[3.636344905],"iteration":645,"passed_time":0.6789001962,"remaining_time":0.3720289001},
{"learn":[3.634754643],"iteration":646,"passed_time":0.6795871977,"remaining_time":0.3707794139},
{"learn":[3.630724975],"iteration":647,"passed_time":0.6802720827,"remaining_time":0.369530514},
{"learn":[3.629408252],"iteration":648,"passed_time":0.6810852841,"remaining_time":0.36835275},
{"learn":[3.62790646],"iteration":649,"passed_time":0.6817338428,"remaining_time":0.3670874538},
{"learn":[3.627388973],"iteration":650,"passed_time":0.6824122684,"remaining_time":0.365840064},
{"learn":[3.625163557],"iteration":651,"passed_time":0.6831954647,"remaining_time":0.3646503401},
{"learn":[3.623701985],"iteration":652,"passed_time":0.6840600702,"remaining_time":0.3635051215},
{"learn":[3.622342639],"iteration":653,"passed_time":0.6848690199,"remaining_time":0.3623313163},
{"learn":[3.621130639],"iteration":654,"passed_time":0.6855656299,"remaining_time":0.3610994539},
{"learn":[3.619125665],"iteration":655,"passed_time":0.6863224787,"remaining_time":0.359900812},
{"learn":[3.618878783],"iteration":656,"passed_time":0.6869964126,"remaining_time":0.3586602276},
{"learn":[3.616207429],"iteration":657,"passed_time":0.6877141835,"remaining_time":0.3574441501},
{"learn":[3.61206486],"iteration":658,"passed_time":0.6884008467,"remaining_time":0.3562134882},
{"learn":[3.611955873],"iteration":659,"passed_time":0.6891415399,"remaining_time":0.3550123085},
{"learn":[3.610713743],"iteration":660,"passed_time":0.6898581031,"remaining_time":0.3538001467},
{"learn":[3.610044025],"iteration":661,"passed_time":0.6905634666,"remaining_time":0.3525837639},
{"learn":[3.607342669],"iteration":662,"passed_time":0.691247911,"remaining_time":0.3513582896},
{"learn":[3.602510618],"iteration":663,"passed_time":0.6919443822,"remaining_time":0.3501405308},
{"learn":[3.600492392],"iteration":664,"passed_time":0.6926071837,"remaining_time":0.3489073783},
{"learn":[3.597171065],"iteration":665,"passed_time":0.6932887429,"remaining_time":0.3476853455},
{"learn":[3.594358798],"iteration":666,"passed_time":0.6940922971,"remaining_time":0.3465258395},
{"learn":[3.593945251],"iteration":667,"passed_time":0.6947932937,"remaining_time":0.3453164274},
{"learn":[3.593607748],"iteration":668,"passed_time":0.6957040269,"remaining_time":0.3442123063},
{"learn":[3.592238714],"iteration":669,"passed_time":0.6963952035,"remaining_time":0.3430006226},
{"learn":[3.590144654],"iteration":670,"passed_time":0.6970899887,"remaining_time":0.3417922597},
{"learn":[3.587151536],"iteration":671,"passed_time":0.6978100514,"remaining_time":0.3405977632},
{"learn":[3.586070865],"iteration":672,"passed_time":0.6985571586,"remaining_time":0.339417817},
{"learn":[3.585102746],"iteration":673,"passed_time":0.6992538733,"remaining_time":0.3382147814},
{"learn":[3.584362847],"iteration":674,"passed_time":0.6998720229,"remaining_time":0.3369754184},
{"learn":[3.581407561],"iteration":675,"passed_time":0.7005904743,"remaining_time":0.335785967},
{"learn":[3.57919422],"iteration":676,"passed_time":0.7013841677,"remaining_time":0.3346338053},
{"learn":[3.577632204],"iteration":677,"passed_time":0.7021536614,"remaining_time":0.3334712079},
{"learn":[3.573911195],"iteration":678,"passed_time":0.7028805269,"remaining_time":0.3322896158},
{"learn":[3.573408216],"iteration":679,"passed_time":0.703577763,"remaining_time":0.3310954179},
{"learn":[3.571076482],"iteration":680,"passed_time":0.7042276745,"remaining_time":0.3298805112},
{"learn":[3.568177107],"iteration":681,"passed_time":0.7048873812,"remaining_time":0.3286718288},
{"learn":[3.564824621],"iteration":682,"passed_time":0.705581296,"remaining_time":0.3274806308},
{"learn":[3.562475026],"iteration":683,"passed_time":0.7062388165,"remaining_time":0.3262740731},
{"learn":[3.561226889],"iteration":684,"passed_time":0.7069513538,"remaining_time":0.3250944182},
{"learn":[3.559383467],"iteration":685,"passed_time":0.7076517028,"remaining_time":0.3239105462},
{"learn":[3.555209766],"iteration":686,"passed_time":0.7084242864,"remaining_time":0.3227609922},
{"learn":[3.55345383],"iteration":687,"passed_time":0.7090641602,"remaining_time":0.3215523517},
{"learn":[3.552300968],"iteration":688,"passed_time":0.7096983679,"remaining_time":0.3203428047},
{"learn":[3.551253986],"iteration":689,"passed_time":0.7103431969,"remaining_time":0.3191396972},
{"learn":[3.549807725],"iteration":690,"passed_time":0.7109947533,"remaining_time":0.3179412138},
{"learn":[3.547992926],"iteration":691,"passed_time":0.7117040436,"remaining_time":0.3167700078},
{"learn":[3.545438607],"iteration":692,"passed_time":0.7125116816,"remaining_time":0.3156437031},
{"learn":[3.543313763],"iteration":693,"passed_time":0.7133640521,"remaining_time":0.3145380403},
{"learn":[3.542962896],"iteration":694,"passed_time":0.7140816177,"remaining_time":0.3133739473},
{"learn":[3.539800465],"iteration":695,"passed_time":0.7148096831,"remaining_time":0.3122157237},
{"learn":[3.53953187],"iteration":696,"passed_time":0.7154995068,"remaining_time":0.3110421099},
{"learn":[3.536332425],"iteration":697,"passed_time":0.7163953709,"remaining_time":0.3099590287},
{"learn":[3.534993327],"iteration":698,"passed_time":0.7170523473,"remaining_time":0.3087736145},
{"learn":[3.531637011],"iteration":699,"passed_time":0.7178189222,"remaining_time":0.3076366809},
{"learn":[3.531040284],"iteration":700,"passed_time":0.7184552497,"remaining_time":0.3064452492},
{"learn":[3.529973872],"iteration":701,"passed_time":0.7190908493,"remaining_time":0.3052550899},
{"learn":[3.527325183],"iteration":702,"passed_time":0.719812353,"remaining_time":0.3041028006},
{"learn":[3.527200815],"iteration":703,"passed_time":0.720655778,"remaining_time":0.3030029976},
{"learn":[3.523459911],"iteration":704,"passed_time":0.7213537149,"remaining_time":0.3018430438},
{"learn":[3.522729934],"iteration":705,"passed_time":0.7220576752,"remaining_time":0.3006869072},
{"learn":[3.522260582],"iteration":706,"passed_time":0.7227333212,"remaining_time":0.2995203156},
{"learn":[3.518641591],"iteration":707,"passed_time":0.7233699391,"remaining_time":0.2983390144},
{"learn":[3.516856405],"iteration":708,"passed_time":0.7240601403,"remaining_time":0.2971812423},
{"learn":[3.515083413],"iteration":709,"passed_time":0.7247903772,"remaining_time":0.29604114},
{"learn":[3.514671214],"iteration":710,"passed_time":0.7254142932,"remaining_time":0.2948589743},
{"learn":[3.512617621],"iteration":711,"passed_time":0.7261341351,"remaining_time":0.2937171783},
{"learn":[3.510747971],"iteration":712,"passed_time":0.726837212,"remaining_time":0.2925698175},
{"learn":[3.508149266],"iteration":713,"passed_time":0.7275221333,"remaining_time":0.2914164287},
{"learn":[3.504557165],"iteration":714,"passed_time":0.7282448941,"remaining_time":0.2902794333},
{"learn":[3.501367208],"iteration":715,"passed_time":0.7290023942,"remaining_time":0.2891573742},
{"learn":[3.497593362],"iteration":716,"passed_time":0.7298039563,"remaining_time":0.2880537233},
{"learn":[3.496291169],"iteration":717,"passed_time":0.7306472997,"remaining_time":0.2869673238},
{"learn":[3.49330374],"iteration":718,"passed_time":0.7312920557,"remaining_time":0.2858039884},
{"learn":[3.490044385],"iteration":719,"passed_time":0.732005074,"remaining_time":0.2846686399},
{"learn":[3.488891789],"iteration":720,"passed_time":0.7327424657,"remaining_time":0.2835438945},
{"learn":[3.486869081],"iteration":721,"passed_time":0.733439407,"remaining_time":0.282404647},
{"learn":[3.486303638],"iteration":722,"passed_time":0.7340965652,"remaining_time":0.2812513811},
{"learn":[3.486035862],"iteration":723,"passed_time":0.7347824806,"remaining_time":0.2801104484},
{"learn":[3.482668951],"iteration":724,"passed_time":0.7354864811,"remaining_time":0.2789776308},
{"learn":[3.47820549],"iteration":725,"passed_time":0.7361317328,"remaining_time":0.277823822},
{"learn":[3.474392283],"iteration":726,"passed_time":0.7368330108,"remaining_time":0.2766924511},
{"learn":[3.472268163],"iteration":727,"passed_time":0.7374856416,"remaining_time":0.2755440859},
{"learn":[3.471209164],"iteration":728,"passed_time":0.7381564215,"remaining_time":0.2744038275},
{"learn":[3.470049971],"iteration":729,"passed_time":0.7388114339,"remaining_time":0.2732590235},
{"learn":[3.469078654],"iteration":730,"passed_time":0.7395186038,"remaining_time":0.272134753},
{"learn":[3.468643292],"iteration":731,"passed_time":0.7401833653,"remaining_time":0.2709960955},
{"learn":[3.468134848],"iteration":732,"passed_time":0.7408235345,"remaining_time":0.2698497732},
{"learn":[3.467820182],"iteration":733,"passed_time":0.7415688244,"remaining_time":0.2687429255},
{"learn":[3.465776156],"iteration":734,"passed_time":0.7422017812,"remaining_time":0.2675965606},
{"learn":[3.463037608],"iteration":735,"passed_time":0.7429056932,"remaining_time":0.2664770421},
{"learn":[3.45965637],"iteration":736,"passed_time":0.7436635849,"remaining_time":0.2653779143},
{"learn":[3.457275091],"iteration":737,"passed_time":0.7443960749,"remaining_time":0.2642706932},
{"learn":[3.455522955],"iteration":738,"passed_time":0.7452245295,"remaining_time":0.2631983792},
{"learn":[3.451270508],"iteration":739,"passed_time":0.7458840025,"remaining_time":0.2620673522},
{"learn":[3.450978947],"iteration":740,"passed_time":0.7465164471,"remaining_time":0.2609281509},
{"learn":[3.450608492],"iteration":741,"passed_time":0.7471627205,"remaining_time":0.2597951238},
{"learn":[3.448122004],"iteration":742,"passed_time":0.7478785355,"remaining_time":0.2586874611},
{"learn":[3.445646714],"iteration":743,"passed_time":0.7485821452,"remaining_time":0.2575766521},
{"learn":[3.44411263],"iteration":744,"passed_time":0.7492430148,"remaining_time":0.2564523071},
{"learn":[3.443264164],"iteration":745,"passed_time":0.7498813246,"remaining_time":0.2553215234},
{"learn":[3.439521363],"iteration":746,"passed_time":0.7506758589,"remaining_time":0.2542449696},
{"learn":[3.436809225],"iteration":747,"passed_time":0.7514867333,"remaining_time":0.2531746748},
{"learn":[3.435509465],"iteration":748,"passed_time":0.7522916533,"remaining_time":0.2521030774},
{"learn":[3.434450277],"iteration":749,"passed_time":0.753119387,"remaining_time":0.2510397957},
{"learn":[3.431786753],"iteration":750,"passed_time":0.7538247125,"remaining_time":0.2499365558},
{"learn":[3.430150302],"iteration":751,"passed_time":0.7544588823,"remaining_time":0.248810908},
{"learn":[3.42696281],"iteration":752,"passed_time":0.7552488217,"remaining_time":0.2477376613},
{"learn":[3.426870334],"iteration":753,"passed_time":0.7559453608,"remaining_time":0.2466346933},
{"learn":[3.425200309],"iteration":754,"passed_time":0.7566333415,"remaining_time":0.2455300247},
{"learn":[3.423383783],"iteration":755,"passed_time":0.757307239,"remaining_time":0.2444219131},
{"learn":[3.422752979],"iteration":756,"passed_time":0.7579997324,"remaining_time":0.2433209181},
{"learn":[3.420845924],"iteration":757,"passed_time":0.7587459174,"remaining_time":0.2422381425},
{"learn":[3.418917862],"iteration":758,"passed_time":0.7594761331,"remaining_time":0.2411511832},
{"learn":[3.417095735],"iteration":759,"passed_time":0.7601876583,"remaining_time":0.2400592605},
{"learn":[3.414391848],"iteration":760,"passed_time":0.7609218357,"remaining_time":0.2389754517},
{"learn":[3.41426711],"iteration":761,"passed_time":0.7615765907,"remaining_time":0.237867754},
{"learn":[3.411976013],"iteration":762,"passed_time":0.7623224013,"remaining_time":0.236789527},
{"learn":[3.408614844],"iteration":763,"passed_time":0.7629539981,"remaining_time":0.2356768895},
{"learn":[3.407906721],"iteration":764,"passed_time":0.7636425653,"remaining_time":0.2345830103},
{"learn":[3.407494015],"iteration":765,"passed_time":0.7643001356,"remaining_time":0.2334807203},
{"learn":[3.406287128],"iteration":766,"passed_time":0.7649308174,"remaining_time":0.2323714217},
{"learn":[3.404600442],"iteration":767,"passed_time":0.7656235288,"remaining_time":0.2312821077},
{"learn":[3.404012662],"iteration":768,"passed_time":0.766236899,"remaining_time":0.2301699918},
{"learn":[3.400398762],"iteration":769,"passed_time":0.7669249825,"remaining_time":0.2290814883},
{"learn":[3.399737714],"iteration":770,"passed_time":0.7676071769,"remaining_time":0.2279922743},
{"learn":[3.399185251],"iteration":771,"passed_time":0.7683221791,"remaining_time":0.2269138042},
{"learn":[3.397245411],"iteration":772,"passed_time":0.7690667522,"remaining_time":0.2258449583},
{"learn":[3.396229831],"iteration":773,"passed_time":0.7697125576,"remaining_time":0.2247481111},
{"learn":[3.394002836],"iteration":774,"passed_time":0.7704581368,"remaining_time":0.2236813946},
{"learn":[3.389617243],"iteration":775,"passed_time":0.7711271573,"remaining_time":0.2225934062},
{"learn":[3.385426488],"iteration":776,"passed_time":0.7718084198,"remaining_time":0.2215100098},
{"learn":[3.385072258],"iteration":777,"passed_time":0.7725245582,"remaining_time":0.2204375989},
{"learn":[3.383842366],"iteration":778,"passed_time":0.7732389094,"remaining_time":0.2193655956},
{"learn":[3.380110746],"iteration":779,"passed_time":0.7739772409,"remaining_time":0.2183012731},
{"learn":[3.378595218],"iteration":780,"passed_time":0.7747074397,"remaining_time":0.2172355049},
{"learn":[3.377371219],"iteration":781,"passed_time":0.7754485731,"remaining_time":0.2161736432},
{"learn":[3.375814782],"iteration":782,"passed_time":0.7762166479,"remaining_time":0.2151200672},
{"learn":[3.374195887],"iteration":783,"passed_time":0.7769705161,"remaining_time":0.2140633054},
{"learn":[3.373704309],"iteration":784,"passed_time":0.7776757963,"remaining_time":0.2129940079},
{"learn":[3.372971757],"iteration":785,"passed_time":0.7783793394,"remaining_time":0.2119251637},
{"learn":[3.371565136],"iteration":786,"passed_time":0.7790590853,"remaining_time":0.2108508071},
{"learn":[3.3700309],"iteration":787,"passed_time":0.7797039335,"remaining_time":0.2097680633},
{"learn":[3.368186663],"iteration":788,"passed_time":0.7803781475,"remaining_time":0.2086942828},
{"learn":[3.366710398],"iteration":789,"passed_time":0.7811401298,"remaining_time":0.2076448446},
{"learn":[3.364598042],"iteration":790,"passed_time":0.7818566714,"remaining_time":0.2065841268},
{"learn":[3.36348442],"iteration":791,"passed_time":0.782571689,"remaining_time":0.2055238779},
{"learn":[3.362001759],"iteration":792,"passed_time":0.7832655664,"remaining_time":0.2044589814},
{"learn":[3.361580401],"iteration":793,"passed_time":0.7839914534,"remaining_time":0.2034033242},
{"learn":[3.359543675],"iteration":794,"passed_time":0.784710801,"remaining_time":0.2023468103},
{"learn":[3.35766119],"iteration":795,"passed_time":0.7854255228,"remaining_time":0.2012899581},
{"learn":[3.354592969],"iteration":796,"passed_time":0.7860883014,"remaining_time":0.2002207342},
{"learn":[3.350985986],"iteration":797,"passed_time":0.7867474432,"remaining_time":0.1991516084},
{"learn":[3.349589624],"iteration":798,"passed_time":0.7874645524,"remaining_time":0.1980980914},
{"learn":[3.349110856],"iteration":799,"passed_time":0.78816515,"remaining_time":0.1970412875},
{"learn":[3.345315441],"iteration":800,"passed_time":0.7889616114,"remaining_time":0.1960091893},
{"learn":[3.34397474],"iteration":801,"passed_time":0.7897609039,"remaining_time":0.1949783778},
{"learn":[3.343800902],"iteration":802,"passed_time":0.7905281188,"remaining_time":0.1939402732},
{"learn":[3.342329465],"iteration":803,"passed_time":0.7912260059,"remaining_time":0.1928859417},
{"learn":[3.34220347],"iteration":804,"passed_time":0.7919071845,"remaining_time":0.1918284484},
{"learn":[3.341279219],"iteration":805,"passed_time":0.7927178226,"remaining_time":0.1908030491},
{"learn":[3.337329521],"iteration":806,"passed_time":0.7935812899,"remaining_time":0.1897908165},
{"learn":[3.336708453],"iteration":807,"passed_time":0.7943004006,"remaining_time":0.1887446496},
{"learn":[3.333252703],"iteration":808,"passed_time":0.7950109858,"remaining_time":0.1876972785},
{"learn":[3.332186769],"iteration":809,"passed_time":0.7957536427,"remaining_time":0.1866582619},
{"learn":[3.330594851],"iteration":810,"passed_time":0.7964396487,"remaining_time":0.1856067739},
{"learn":[3.327867442],"iteration":811,"passed_time":0.7971786436,"remaining_time":0.1845684544},
{"learn":[3.327563111],"iteration":812,"passed_time":0.7978407443,"remaining_time":0.1835131847},
{"learn":[3.326308994],"iteration":813,"passed_time":0.7984523767,"remaining_time":0.182447349},
{"learn":[3.326249879],"iteration":814,"passed_time":0.7991264166,"remaining_time":0.1813967939},
{"learn":[3.322336238],"iteration":815,"passed_time":0.7999415958,"remaining_time":0.1803789873},
{"learn":[3.320491154],"iteration":816,"passed_time":0.8007098156,"remaining_time":0.1793511582},
{"learn":[3.320434271],"iteration":817,"passed_time":0.8014891372,"remaining_time":0.178326434},
{"learn":[3.319609638],"iteration":818,"passed_time":0.8022634888,"remaining_time":0.1773012106},
{"learn":[3.316182682],"iteration":819,"passed_time":0.8030247968,"remaining_time":0.1762737359},
{"learn":[3.313126612],"iteration":820,"passed_time":0.8037428804,"remaining_time":0.1752374855},
{"learn":[3.311222803],"iteration":821,"passed_time":0.8045343642,"remaining_time":0.1742179037},
{"learn":[3.309627335],"iteration":822,"passed_time":0.8054095052,"remaining_time":0.1732168681},
{"learn":[3.307974895],"iteration":823,"passed_time":0.8061602375,"remaining_time":0.1721895653},
{"learn":[3.307321505],"iteration":824,"passed_time":0.8068990171,"remaining_time":0.1711603976},
{"learn":[3.306759087],"iteration":825,"passed_time":0.8076864377,"remaining_time":0.1701421794},
{"learn":[3.30484037],"iteration":826,"passed_time":0.808558825,"remaining_time":0.1691422935},
{"learn":[3.30201994],"iteration":827,"passed_time":0.8093817862,"remaining_time":0.1681324483},
{"learn":[3.299302297],"iteration":828,"passed_time":0.8101611144,"remaining_time":0.1671140537},
{"learn":[3.298132671],"iteration":829,"passed_time":0.8108108228,"remaining_time":0.1660696866},
{"learn":[3.296976183],"iteration":830,"passed_time":0.8114651126,"remaining_time":0.165027201},
{"learn":[3.293144745],"iteration":831,"passed_time":0.8121600681,"remaining_time":0.1639938599},
{"learn":[3.290284404],"iteration":832,"passed_time":0.8128256997,"remaining_time":0.1629554524},
{"learn":[3.288285745],"iteration":833,"passed_time":0.8135655091,"remaining_time":0.1619327033},
{"learn":[3.286662667],"iteration":834,"passed_time":0.8142463456,"remaining_time":0.1608989785},
{"learn":[3.285692682],"iteration":835,"passed_time":0.8150250433,"remaining_time":0.1598852956},
{"learn":[3.284565611],"iteration":836,"passed_time":0.8157799842,"remaining_time":0.1588675477},
{"learn":[3.283897383],"iteration":837,"passed_time":0.8166160257,"remaining_time":0.1578661052},
{"learn":[3.280712855],"iteration":838,"passed_time":0.8173643884,"remaining_time":0.1568482319},
{"learn":[3.280468341],"iteration":839,"passed_time":0.818106108,"remaining_time":0.1558297349},
{"learn":[3.277814895],"iteration":840,"passed_time":0.818897511,"remaining_time":0.1548212892},
{"learn":[3.276316385],"iteration":841,"passed_time":0.8197481488,"remaining_time":0.1538244745},
{"learn":[3.27557063],"iteration":842,"passed_time":0.8205436887,"remaining_time":0.1528177451},
{"learn":[3.27499628],"iteration":843,"passed_time":0.8212765154,"remaining_time":0.1517999246},
{"learn":[3.273569958],"iteration":844,"passed_time":0.8219986066,"remaining_time":0.1507808095},
{"learn":[3.269665595],"iteration":845,"passed_time":0.8229310561,"remaining_time":0.1498006887},
{"learn":[3.267984685],"iteration":846,"passed_time":0.8237886445,"remaining_time":0.1488071577},
{"learn":[3.267702508],"iteration":847,"passed_time":0.8246074993,"remaining_time":0.1478070046},
{"learn":[3.266671924],"iteration":848,"passed_time":0.8253640309,"remaining_time":0.146796194},
{"learn":[3.265359825],"iteration":849,"passed_time":0.8261238314,"remaining_time":0.1457865585},
{"learn":[3.2618983],"iteration":850,"passed_time":0.826795107,"remaining_time":0.1447620105},
{"learn":[3.260456253],"iteration":851,"passed_time":0.8274501753,"remaining_time":0.1437354765},
{"learn":[3.258389147],"iteration":852,"passed_time":0.8281400275,"remaining_time":0.1427158078},
{"learn":[3.258108469],"iteration":853,"passed_time":0.8288148192,"remaining_time":0.1416943368},
{"learn":[3.256424936],"iteration":854,"passed_time":0.829511167,"remaining_time":0.1406773324},
{"learn":[3.254817983],"iteration":855,"passed_time":0.8301837734,"remaining_time":0.1396570834},
{"learn":[3.253898449],"iteration":856,"passed_time":0.8309151609,"remaining_time":0.1386474539},
{"learn":[3.253023652],"iteration":857,"passed_time":0.8316070262,"remaining_time":0.1376319321},
{"learn":[3.252845542],"iteration":858,"passed_time":0.8322600049,"remaining_time":0.1366107808},
{"learn":[3.252316026],"iteration":859,"passed_time":0.8329999453,"remaining_time":0.1356046423},
{"learn":[3.24975301],"iteration":860,"passed_time":0.8337148838,"remaining_time":0.1345950858},
{"learn":[3.249151075],"iteration":861,"passed_time":0.8344123506,"remaining_time":0.1335834158},
{"learn":[3.246257135],"iteration":862,"passed_time":0.8352186138,"remaining_time":0.1325897452},
{"learn":[3.243826471],"iteration":863,"passed_time":0.8359604751,"remaining_time":0.1315863711},
{"learn":[3.243190653],"iteration":864,"passed_time":0.8367124869,"remaining_time":0.1305851858},
{"learn":[3.24008797],"iteration":865,"passed_time":0.8373708967,"remaining_time":0.1295700926},
{"learn":[3.240036811],"iteration":866,"passed_time":0.8381213455,"remaining_time":0.1285699411},
{"learn":[3.238676314],"iteration":867,"passed_time":0.8388247207,"remaining_time":0.1275632064},
{"learn":[3.237848782],"iteration":868,"passed_time":0.8395933721,"remaining_time":0.1265670101},
{"learn":[3.236405498],"iteration":869,"passed_time":0.8403668772,"remaining_time":0.1255720621},
{"learn":[3.233378068],"iteration":870,"passed_time":0.8411400454,"remaining_time":0.1245775727},
{"learn":[3.233169169],"iteration":871,"passed_time":0.8418213762,"remaining_time":0.1235701103},
{"learn":[3.232434885],"iteration":872,"passed_time":0.8424841685,"remaining_time":0.122560698},
{"learn":[3.229978115],"iteration":873,"passed_time":0.8432519401,"remaining_time":0.1215672133},
{"learn":[3.229648848],"iteration":874,"passed_time":0.843960385,"remaining_time":0.1205657693},
{"learn":[3.227208761],"iteration":875,"passed_time":0.844679326,"remaining_time":0.1195664799},
{"learn":[3.226258869],"iteration":876,"passed_time":0.8454158984,"remaining_time":0.1185703027},
{"learn":[3.225331995],"iteration":877,"passed_time":0.8461653157,"remaining_time":0.1175765017},
{"learn":[3.221968268],"iteration":878,"passed_time":0.8468276115,"remaining_time":0.1165712639},
{"learn":[3.221166317],"iteration":879,"passed_time":0.8475774971,"remaining_time":0.1155787496},
{"learn":[3.220047503],"iteration":880,"passed_time":0.8482803843,"remaining_time":0.1145804378},
{"learn":[3.21982781],"iteration":881,"passed_time":0.8489695231,"remaining_time":0.1135809566},
{"learn":[3.216693405],"iteration":882,"passed_time":0.849793809,"remaining_time":0.1126000857},
{"learn":[3.214798761],"iteration":883,"passed_time":0.8506180496,"remaining_time":0.1116195631},
{"learn":[3.214395085],"iteration":884,"passed_time":0.8513253162,"remaining_time":0.1106241936},
{"learn":[3.213470696],"iteration":885,"passed_time":0.8520351451,"remaining_time":0.1096298042},
{"learn":[3.211595017],"iteration":886,"passed_time":0.8527965281,"remaining_time":0.1086426242},
{"learn":[3.210965255],"iteration":887,"passed_time":0.8534934522,"remaining_time":0.1076478228},
{"learn":[3.209413583],"iteration":888,"passed_time":0.8541507434,"remaining_time":0.106648743},
{"learn":[3.208331683],"iteration":889,"passed_time":0.8548108452,"remaining_time":0.1056507786},
{"learn":[3.207110711],"iteration":890,"passed_time":0.8554918421,"remaining_time":0.1046561288},
{"learn":[3.204519413],"iteration":891,"passed_time":0.8562692675,"remaining_time":0.1036738575},
{"learn":[3.201421296],"iteration":892,"passed_time":0.8569632563,"remaining_time":0.1026820475},
{"learn":[3.200691259],"iteration":893,"passed_time":0.8576284768,"remaining_time":0.1016874928},
{"learn":[3.200485067],"iteration":894,"passed_time":0.8583062072,"remaining_time":0.1006951416},
{"learn":[3.197467568],"iteration":895,"passed_time":0.8590411022,"remaining_time":0.09971012793},
{"learn":[3.195838544],"iteration":896,"passed_time":0.8597340306,"remaining_time":0.09872085301},
{"learn":[3.195671746],"iteration":897,"passed_time":0.8604534203,"remaining_time":0.09773524373},
{"learn":[3.194213094],"iteration":898,"passed_time":0.8611886564,"remaining_time":0.096752007},
{"learn":[3.192884691],"iteration":899,"passed_time":0.8618606074,"remaining_time":0.09576228971},
{"learn":[3.188364239],"iteration":900,"passed_time":0.8625896317,"remaining_time":0.09477954887},
{"learn":[3.185219478],"iteration":901,"passed_time":0.8632962908,"remaining_time":0.09379494068},
{"learn":[3.184120387],"iteration":902,"passed_time":0.8641835535,"remaining_time":0.0928303485},
{"learn":[3.183725321],"iteration":903,"passed_time":0.8649693368,"remaining_time":0.09185515081},
{"learn":[3.181264554],"iteration":904,"passed_time":0.8658692819,"remaining_time":0.09089235556},
{"learn":[3.180741589],"iteration":905,"passed_time":0.8665874704,"remaining_time":0.08991084129},
{"learn":[3.179782639],"iteration":906,"passed_time":0.8672466125,"remaining_time":0.08892385332},
{"learn":[3.176377564],"iteration":907,"passed_time":0.8679465686,"remaining_time":0.08794172281},
{"learn":[3.174078182],"iteration":908,"passed_time":0.8686901306,"remaining_time":0.08696457853},
{"learn":[3.171242379],"iteration":909,"passed_time":0.8694006695,"remaining_time":0.0859846816},
{"learn":[3.170421012],"iteration":910,"passed_time":0.870085525,"remaining_time":0.08500286688},
{"learn":[3.170087224],"iteration":911,"passed_time":0.8707269154,"remaining_time":0.08401750938},
{"learn":[3.167303059],"iteration":912,"passed_time":0.8713835658,"remaining_time":0.08303435951},
{"learn":[3.16705966],"iteration":913,"passed_time":0.8720711139,"remaining_time":0.08205483128},
{"learn":[3.165667683],"iteration":914,"passed_time":0.8727728342,"remaining_time":0.08107725782},
{"learn":[3.164689733],"iteration":915,"passed_time":0.8734682159,"remaining_time":0.08009970539},
{"learn":[3.163311455],"iteration":916,"passed_time":0.8741973602,"remaining_time":0.07912582431},
{"learn":[3.159425016],"iteration":917,"passed_time":0.8749713988,"remaining_time":0.0781564866},
{"learn":[3.159327058],"iteration":918,"passed_time":0.8756772975,"remaining_time":0.07718156812},
{"learn":[3.15819426],"iteration":919,"passed_time":0.8764036796,"remaining_time":0.07620901562},
{"learn":[3.157086603],"iteration":920,"passed_time":0.8771440941,"remaining_time":0.07523820134},
{"learn":[3.153354154],"iteration":921,"passed_time":0.877872896,"remaining_time":0.07426690443},
{"learn":[3.153261317],"iteration":922,"passed_time":0.8785207902,"remaining_time":0.07328938336},
{"learn":[3.153168454],"iteration":923,"passed_time":0.8791580488,"remaining_time":0.07231170098},
{"learn":[3.152080399],"iteration":924,"passed_time":0.8799730961,"remaining_time":0.07134916995},
{"learn":[3.151635144],"iteration":925,"passed_time":0.8807354356,"remaining_time":0.07038274539},
{"learn":[3.147762655],"iteration":926,"passed_time":0.8815352345,"remaining_time":0.06941971102},
{"learn":[3.147172317],"iteration":927,"passed_time":0.8822927833,"remaining_time":0.06845375043},
{"learn":[3.146254125],"iteration":928,"passed_time":0.8829435419,"remaining_time":0.06748007694},
{"learn":[3.144869828],"iteration":929,"passed_time":0.8836358244,"remaining_time":0.06651022334},
{"learn":[3.143466218],"iteration":930,"passed_time":0.8845243453,"remaining_time":0.06555551002},
{"learn":[3.141919643],"iteration":931,"passed_time":0.8852623491,"remaining_time":0.0645899568},
{"learn":[3.141054135],"iteration":932,"passed_time":0.8860490343,"remaining_time":0.06362838725},
{"learn":[3.139390417],"iteration":933,"passed_time":0.8870123498,"remaining_time":0.06267967354},
{"learn":[3.139025283],"iteration":934,"passed_time":0.8876934626,"remaining_time":0.06171131024},
{"learn":[3.137824183],"iteration":935,"passed_time":0.8883277105,"remaining_time":0.06074035627},
{"learn":[3.135620453],"iteration":936,"passed_time":0.8891089934,"remaining_time":0.05978000703},
{"learn":[3.13443178],"iteration":937,"passed_time":0.8898145524,"remaining_time":0.05881503438},
{"learn":[3.132765713],"iteration":938,"passed_time":0.8906031075,"remaining_time":0.05785600592},
{"learn":[3.131434124],"iteration":939,"passed_time":0.8913391187,"remaining_time":0.0568939863},
{"learn":[3.128384262],"iteration":940,"passed_time":0.8921378729,"remaining_time":0.05593638098},
{"learn":[3.128120455],"iteration":941,"passed_time":0.8927977553,"remaining_time":0.05497056243},
{"learn":[3.126314615],"iteration":942,"passed_time":0.8935547089,"remaining_time":0.05401126024},
{"learn":[3.125409666],"iteration":943,"passed_time":0.8943380118,"remaining_time":0.05305394986},
{"learn":[3.123072589],"iteration":944,"passed_time":0.8951100298,"remaining_time":0.05209635094},
{"learn":[3.122921099],"iteration":945,"passed_time":0.8959632241,"remaining_time":0.05114377812},
{"learn":[3.122182662],"iteration":946,"passed_time":0.8966667488,"remaining_time":0.05018303874},
{"learn":[3.120040951],"iteration":947,"passed_time":0.8974154577,"remaining_time":0.04922532046},
{"learn":[3.118767799],"iteration":948,"passed_time":0.8981615632,"remaining_time":0.04826790276},
{"learn":[3.118203218],"iteration":949,"passed_time":0.8988155961,"remaining_time":0.04730608401},
{"learn":[3.116343362],"iteration":950,"passed_time":0.8995711672,"remaining_time":0.04635014426},
{"learn":[3.11480829],"iteration":951,"passed_time":0.9002594225,"remaining_time":0.04539123138},
{"learn":[3.112607903],"iteration":952,"passed_time":0.9009378228,"remaining_time":0.04443240049},
{"learn":[3.111661241],"iteration":953,"passed_time":0.9017049071,"remaining_time":0.04347843367},
{"learn":[3.110249676],"iteration":954,"passed_time":0.9024256013,"remaining_time":0.04252267231},
{"learn":[3.107333579],"iteration":955,"passed_time":0.903166036,"remaining_time":0.04156831128},
{"learn":[3.107149851],"iteration":956,"passed_time":0.9037954905,"remaining_time":0.04060941075},
{"learn":[3.106867336],"iteration":957,"passed_time":0.9044456796,"remaining_time":0.03965210704},
{"learn":[3.10364681],"iteration":958,"passed_time":0.9052072015,"remaining_time":0.03870020361},
{"learn":[3.102703811],"iteration":959,"passed_time":0.9058228241,"remaining_time":0.03774261767},
{"learn":[3.101469264],"iteration":960,"passed_time":0.9065175054,"remaining_time":0.03678895183},
{"learn":[3.09863569],"iteration":961,"passed_time":0.9072174224,"remaining_time":0.03583603124},
{"learn":[3.09645939],"iteration":962,"passed_time":0.9079799817,"remaining_time":0.03488604291},
{"learn":[3.096240186],"iteration":963,"passed_time":0.9086646911,"remaining_time":0.03393353618},
{"learn":[3.094838828],"iteration":964,"passed_time":0.9093352865,"remaining_time":0.03298107257},
{"learn":[3.094176802],"iteration":965,"passed_time":0.91004131,"remaining_time":0.03203043948},
{"learn":[3.093182279],"iteration":966,"passed_time":0.910781573,"remaining_time":0.03108148077},
{"learn":[3.090150687],"iteration":967,"passed_time":0.9114532137,"remaining_time":0.03013068475},
{"learn":[3.088612829],"iteration":968,"passed_time":0.9121382567,"remaining_time":0.02918089366},
{"learn":[3.087153684],"iteration":969,"passed_time":0.9129979322,"remaining_time":0.02823704945},
{"learn":[3.085866843],"iteration":970,"passed_time":0.9137464553,"remaining_time":0.02729005891},
{"learn":[3.082669094],"iteration":971,"passed_time":0.9144208267,"remaining_time":0.02634134069},
{"learn":[3.081047548],"iteration":972,"passed_time":0.9151071251,"remaining_time":0.02539351735},
{"learn":[3.079684322],"iteration":973,"passed_time":0.9157594456,"remaining_time":0.02444532401},
{"learn":[3.07613431],"iteration":974,"passed_time":0.9165169523,"remaining_time":0.02350043467},
{"learn":[3.074005935],"iteration":975,"passed_time":0.9172335713,"remaining_time":0.02255492388},
{"learn":[3.072988853],"iteration":976,"passed_time":0.9179287106,"remaining_time":0.02160937599},
{"learn":[3.072344268],"iteration":977,"passed_time":0.9186025629,"remaining_time":0.02066386133},
{"learn":[3.070654438],"iteration":978,"passed_time":0.9193021762,"remaining_time":0.01971945424},
{"learn":[3.069724506],"iteration":979,"passed_time":0.9199213868,"remaining_time":0.01877390585},
{"learn":[3.067763166],"iteration":980,"passed_time":0.9206400803,"remaining_time":0.01783094957},
{"learn":[3.066737893],"iteration":981,"passed_time":0.9214069298,"remaining_time":0.01688933272},
{"learn":[3.065248174],"iteration":982,"passed_time":0.9221181098,"remaining_time":0.01594710871},
{"learn":[3.063186837],"iteration":983,"passed_time":0.9227849471,"remaining_time":0.01500463329},
{"learn":[3.062880371],"iteration":984,"passed_time":0.9234969245,"remaining_time":0.01406340494},
{"learn":[3.061288645],"iteration":985,"passed_time":0.9242049494,"remaining_time":0.01312258549},
{"learn":[3.059970575],"iteration":986,"passed_time":0.9248878586,"remaining_time":0.01218190695},
{"learn":[3.059576341],"iteration":987,"passed_time":0.92564355,"remaining_time":0.01124263421},
{"learn":[3.058175919],"iteration":988,"passed_time":0.9263419164,"remaining_time":0.01030309513},
{"learn":[3.056830702],"iteration":989,"passed_time":0.9270240073,"remaining_time":0.009363878861},
{"learn":[3.056336579],"iteration":990,"passed_time":0.9276935591,"remaining_time":0.008425067641},
{"learn":[3.055810414],"iteration":991,"passed_time":0.9284428505,"remaining_time":0.007487442343},
{"learn":[3.055476518],"iteration":992,"passed_time":0.9292672049,"remaining_time":0.006550725513},
{"learn":[3.053331734],"iteration":993,"passed_time":0.9300401715,"remaining_time":0.005613924577},
{"learn":[3.050890374],"iteration":994,"passed_time":0.9308341855,"remaining_time":0.004677558721},
{"learn":[3.04972623],"iteration":995,"passed_time":0.931648616,"remaining_time":0.003741560707},
{"learn":[3.047217327],"iteration":996,"passed_time":0.9324071796,"remaining_time":0.002805638454},
{"learn":[3.047155483],"iteration":997,"passed_time":0.9331472129,"remaining_time":0.001870034495},
{"learn":[3.04430671],"iteration":998,"passed_time":0.9338639505,"remaining_time":0.0009347987493},
{"learn":[3.042664195],"iteration":999,"passed_time":0.9346104729,"remaining_time":0}
]}